[
	{
		"SIGUN_NM": "여주시",
		"CMPNM_NM": "(주)삼부고속관광",
		"INDUTYPE_NM": "여행-관광여행",
		"REFINE_ROADNM_ADDR": "경기도 여주시 점동면 들말길 66-4",
		"REFINE_LOTNO_ADDR": "경기도 여주시 점동면 덕평리 387-9번지",
		"TELNO": "",
		"REFINE_ZIPNO": "12667",
		"REFINE_WGS84_LAT": "37.1726334635",
		"REFINE_WGS84_LOGT": "127.6503021381",
		"DATA_STD_DE": "2020-08-18"
	},
	{
		"SIGUN_NM": "여주시",
		"CMPNM_NM": "(주)에이스비젼",
		"INDUTYPE_NM": "자동차정비 유지-주차장",
		"REFINE_ROADNM_ADDR": "경기도 여주시 점동면 선사길 237",
		"REFINE_LOTNO_ADDR": "경기도 여주시 점동면 흔암리 149-9번지",
		"TELNO": "",
		"REFINE_ZIPNO": "12666",
		"REFINE_WGS84_LAT": "37.2411503720",
		"REFINE_WGS84_LOGT": "127.6759752113",
		"DATA_STD_DE": "2020-08-18"
	},
	{
		"SIGUN_NM": "여주시",
		"CMPNM_NM": "(주)우리여행사",
		"INDUTYPE_NM": "여행-관광여행",
		"REFINE_ROADNM_ADDR": "경기도 여주시 점동면 성주로 674-3",
		"REFINE_LOTNO_ADDR": "경기도 여주시 점동면 성신리 218-2번지",
		"TELNO": "",
		"REFINE_ZIPNO": "12668",
		"REFINE_WGS84_LAT": "37.1676251367",
		"REFINE_WGS84_LOGT": "127.6678073343",
		"DATA_STD_DE": "2020-08-18"
	},
	{
		"SIGUN_NM": "여주시",
		"CMPNM_NM": "(주)장안산업개발",
		"INDUTYPE_NM": "건축자재-기타건축자재",
		"REFINE_ROADNM_ADDR": "경기도 여주시 점동면 안평로 94",
		"REFINE_LOTNO_ADDR": "경기도 여주시 점동면 장안리 611-10번지",
		"TELNO": "",
		"REFINE_ZIPNO": "12665",
		"REFINE_WGS84_LAT": "37.2069752876",
		"REFINE_WGS84_LOGT": "127.7003846257",
		"DATA_STD_DE": "2020-08-18"
	},
	{
		"SIGUN_NM": "여주시",
		"CMPNM_NM": "SD스포츠아카데미",
		"INDUTYPE_NM": "학원-예•체능계학원 ",
		"REFINE_ROADNM_ADDR": "",
		"REFINE_LOTNO_ADDR": "경기도 여주시 점동면 당진리 9-1번지",
		"TELNO": "",
		"REFINE_ZIPNO": "12668",
		"REFINE_WGS84_LAT": "37.1653435747",
		"REFINE_WGS84_LOGT": "127.6932752175",
		"DATA_STD_DE": "2020-08-18"
	},
	{
		"SIGUN_NM": "여주시",
		"CMPNM_NM": "YJ푸드",
		"INDUTYPE_NM": "음료식품-기타음료식품",
		"REFINE_ROADNM_ADDR": "경기도 여주시 점동면 장여로 1318-16",
		"REFINE_LOTNO_ADDR": "경기도 여주시 점동면 처리 468-5번지",
		"TELNO": "",
		"REFINE_ZIPNO": "12666",
		"REFINE_WGS84_LAT": "37.2174281696",
		"REFINE_WGS84_LOGT": "127.6678161451",
		"DATA_STD_DE": "2020-08-18"
	},
	{
		"SIGUN_NM": "여주시",
		"CMPNM_NM": "가래울해장국",
		"INDUTYPE_NM": "일반휴게음식-일반한식",
		"REFINE_ROADNM_ADDR": "경기도 여주시 점동면 가래울길 29",
		"REFINE_LOTNO_ADDR": "경기도 여주시 점동면 사곡리 372번지",
		"TELNO": "",
		"REFINE_ZIPNO": "12665",
		"REFINE_WGS84_LAT": "37.2051306913",
		"REFINE_WGS84_LOGT": "127.6755872747",
		"DATA_STD_DE": "2020-08-18"
	},
	{
		"SIGUN_NM": "여주시",
		"CMPNM_NM": "가을애 양곡직판장",
		"INDUTYPE_NM": "음료식품-미곡상",
		"REFINE_ROADNM_ADDR": "경기도 여주시 점동면 선사길 144-25",
		"REFINE_LOTNO_ADDR": "경기도 여주시 점동면 흔암리 251번지",
		"TELNO": "",
		"REFINE_ZIPNO": "12666",
		"REFINE_WGS84_LAT": "37.2332847206",
		"REFINE_WGS84_LOGT": "127.6735218530",
		"DATA_STD_DE": "2020-08-18"
	},
	{
		"SIGUN_NM": "여주시",
		"CMPNM_NM": "강나루토종순대국",
		"INDUTYPE_NM": "일반휴게음식-일반한식",
		"REFINE_ROADNM_ADDR": "경기도 여주시 점동면 청안로 135",
		"REFINE_LOTNO_ADDR": "경기도 여주시 점동면 청안리 604-36번지",
		"TELNO": "",
		"REFINE_ZIPNO": "12667",
		"REFINE_WGS84_LAT": "37.2066279180",
		"REFINE_WGS84_LOGT": "127.6623265041",
		"DATA_STD_DE": "2020-08-18"
	},
	{
		"SIGUN_NM": "여주시",
		"CMPNM_NM": "갤러리노래연습장",
		"INDUTYPE_NM": "레저업소-노 래 방",
		"REFINE_ROADNM_ADDR": "경기도 여주시 점동면 청안리길 25",
		"REFINE_LOTNO_ADDR": "경기도 여주시 점동면 청안리 141-4번지",
		"TELNO": "",
		"REFINE_ZIPNO": "12667",
		"REFINE_WGS84_LAT": "37.2057116099",
		"REFINE_WGS84_LOGT": "127.6600255846",
		"DATA_STD_DE": "2020-08-18"
	},
	{
		"SIGUN_NM": "여주시",
		"CMPNM_NM": "건우분식",
		"INDUTYPE_NM": "일반휴게음식-일반한식",
		"REFINE_ROADNM_ADDR": "경기도 여주시 점동면 청안로 134",
		"REFINE_LOTNO_ADDR": "경기도 여주시 점동면 청안리 124-3번지",
		"TELNO": "",
		"REFINE_ZIPNO": "12667",
		"REFINE_WGS84_LAT": "37.2062220373",
		"REFINE_WGS84_LOGT": "127.6625059464",
		"DATA_STD_DE": "2020-08-18"
	},
	{
		"SIGUN_NM": "여주시",
		"CMPNM_NM": "경수주유소",
		"INDUTYPE_NM": "연료판매점-SK주유소",
		"REFINE_ROADNM_ADDR": "경기도 여주시 점동면 장여로 653",
		"REFINE_LOTNO_ADDR": "경기도 여주시 점동면 덕평리 575-1번지",
		"TELNO": "",
		"REFINE_ZIPNO": "12667",
		"REFINE_WGS84_LAT": "37.1660679631",
		"REFINE_WGS84_LOGT": "127.6456373060",
		"DATA_STD_DE": "2020-08-18"
	},
	{
		"SIGUN_NM": "여주시",
		"CMPNM_NM": "고려불상조성소",
		"INDUTYPE_NM": "신변잡화-기념품점",
		"REFINE_ROADNM_ADDR": "경기도 여주시 점동면 성주로 490",
		"REFINE_LOTNO_ADDR": "경기도 여주시 점동면 관한리 435번지",
		"TELNO": "",
		"REFINE_ZIPNO": "12668",
		"REFINE_WGS84_LAT": "37.1553924227",
		"REFINE_WGS84_LOGT": "127.6549191782",
		"DATA_STD_DE": "2020-08-18"
	},
	{
		"SIGUN_NM": "여주시",
		"CMPNM_NM": "고려약국",
		"INDUTYPE_NM": "약국-약국",
		"REFINE_ROADNM_ADDR": "경기도 여주시 점동면 청안로 123",
		"REFINE_LOTNO_ADDR": "경기도 여주시 점동면 청안리 127-4번지",
		"TELNO": "",
		"REFINE_ZIPNO": "12667",
		"REFINE_WGS84_LAT": "37.2056102824",
		"REFINE_WGS84_LOGT": "127.6616256229",
		"DATA_STD_DE": "2020-08-18"
	},
	{
		"SIGUN_NM": "여주시",
		"CMPNM_NM": "공감",
		"INDUTYPE_NM": "학원-기타 교육기관",
		"REFINE_ROADNM_ADDR": "경기도 여주시 점동면 청안로 145-3",
		"REFINE_LOTNO_ADDR": "경기도 여주시 점동면 청안리 159-2번지 202호",
		"TELNO": "",
		"REFINE_ZIPNO": "12667",
		"REFINE_WGS84_LAT": "37.2074388296",
		"REFINE_WGS84_LOGT": "127.6625874430",
		"DATA_STD_DE": "2020-08-18"
	},
	{
		"SIGUN_NM": "여주시",
		"CMPNM_NM": "광희머리방",
		"INDUTYPE_NM": "보건위생-미용원",
		"REFINE_ROADNM_ADDR": "경기도 여주시 점동면 청안로 158",
		"REFINE_LOTNO_ADDR": "경기도 여주시 점동면 청안리 164번지",
		"TELNO": "",
		"REFINE_ZIPNO": "12667",
		"REFINE_WGS84_LAT": "37.2080584686",
		"REFINE_WGS84_LOGT": "127.6642792342",
		"DATA_STD_DE": "2020-08-18"
	},
	{
		"SIGUN_NM": "여주시",
		"CMPNM_NM": "국민순대국",
		"INDUTYPE_NM": "일반휴게음식-스넥",
		"REFINE_ROADNM_ADDR": "경기도 여주시 점동면 장여로 1331",
		"REFINE_LOTNO_ADDR": "경기도 여주시 점동면 처리 520-1번지",
		"TELNO": "",
		"REFINE_ZIPNO": "12666",
		"REFINE_WGS84_LAT": "37.2188094509",
		"REFINE_WGS84_LOGT": "127.6663088448",
		"DATA_STD_DE": "2020-08-18"
	},
	{
		"SIGUN_NM": "여주시",
		"CMPNM_NM": "국제종합기계(주)여주대리점",
		"INDUTYPE_NM": "농업-농기계",
		"REFINE_ROADNM_ADDR": "경기도 여주시 점동면 신이길 12",
		"REFINE_LOTNO_ADDR": "경기도 여주시 점동면 성신리 79-16",
		"TELNO": "",
		"REFINE_ZIPNO": "12668",
		"REFINE_WGS84_LAT": "37.1703330686",
		"REFINE_WGS84_LOGT": "127.6715304882",
		"DATA_STD_DE": "2020-08-18"
	},
	{
		"SIGUN_NM": "여주시",
		"CMPNM_NM": "기린가구",
		"INDUTYPE_NM": "직물-카페트,커튼,천막,지물",
		"REFINE_ROADNM_ADDR": "경기도 여주시 점동면 부구로 5",
		"REFINE_LOTNO_ADDR": "경기도 여주시 점동면 청안리 104-11번지",
		"TELNO": "",
		"REFINE_ZIPNO": "12667",
		"REFINE_WGS84_LAT": "37.2033204132",
		"REFINE_WGS84_LOGT": "127.6618348518",
		"DATA_STD_DE": "2020-08-18"
	},
	{
		"SIGUN_NM": "여주시",
		"CMPNM_NM": "기린인테리어",
		"INDUTYPE_NM": "주방용구-주방용구",
		"REFINE_ROADNM_ADDR": "경기도 여주시 점동면 부구로 5",
		"REFINE_LOTNO_ADDR": "경기도 여주시 점동면 청안리 104-11번지",
		"TELNO": "",
		"REFINE_ZIPNO": "12667",
		"REFINE_WGS84_LAT": "37.2033204132",
		"REFINE_WGS84_LOGT": "127.6618348518",
		"DATA_STD_DE": "2020-08-18"
	},
	{
		"SIGUN_NM": "여주시",
		"CMPNM_NM": "김가네치킨",
		"INDUTYPE_NM": "일반휴게음식-스넥",
		"REFINE_ROADNM_ADDR": "경기도 여주시 점동면 청안로 130-23",
		"REFINE_LOTNO_ADDR": "경기도 여주시 점동면 청안리 131-1번지",
		"TELNO": "",
		"REFINE_ZIPNO": "12667",
		"REFINE_WGS84_LAT": "37.2056627775",
		"REFINE_WGS84_LOGT": "127.6627864820",
		"DATA_STD_DE": "2020-08-18"
	},
	{
		"SIGUN_NM": "여주시",
		"CMPNM_NM": "꿈의궁전",
		"INDUTYPE_NM": "숙박업-여관/기타숙박업",
		"REFINE_ROADNM_ADDR": "경기도 여주시 점동면 장여로 883",
		"REFINE_LOTNO_ADDR": "경기도 여주시 점동면 덕평리 170-6번지",
		"TELNO": "",
		"REFINE_ZIPNO": "12667",
		"REFINE_WGS84_LAT": "37.1796209970",
		"REFINE_WGS84_LOGT": "127.6627643814",
		"DATA_STD_DE": "2020-08-18"
	},
	{
		"SIGUN_NM": "여주시",
		"CMPNM_NM": "나루터김밥",
		"INDUTYPE_NM": "일반휴게음식-스넥",
		"REFINE_ROADNM_ADDR": "경기도 여주시 점동면 청안로 140",
		"REFINE_LOTNO_ADDR": "경기도 여주시 점동면 청안리 123-3번지",
		"TELNO": "",
		"REFINE_ZIPNO": "12667",
		"REFINE_WGS84_LAT": "37.2067085191",
		"REFINE_WGS84_LOGT": "127.6627098413",
		"DATA_STD_DE": "2020-08-18"
	},
	{
		"SIGUN_NM": "여주시",
		"CMPNM_NM": "노총매점",
		"INDUTYPE_NM": "음료식품-기타음료식품",
		"REFINE_ROADNM_ADDR": "경기도 여주시 점동면 장여로 987-189",
		"REFINE_LOTNO_ADDR": "경기도 여주시 점동면 덕평리 9-2번지",
		"TELNO": "",
		"REFINE_ZIPNO": "12667",
		"REFINE_WGS84_LAT": "37.1916445474",
		"REFINE_WGS84_LOGT": "127.6570551267",
		"DATA_STD_DE": "2020-08-18"
	},
	{
		"SIGUN_NM": "여주시",
		"CMPNM_NM": "농업회사법인 우주미래식량 주식회사",
		"INDUTYPE_NM": "음료식품-미곡상",
		"REFINE_ROADNM_ADDR": "경기도 여주시 점동면 점동로 664-160",
		"REFINE_LOTNO_ADDR": "경기도 여주시 점동면 삼합리 648-9번지",
		"TELNO": "",
		"REFINE_ZIPNO": "12665",
		"REFINE_WGS84_LAT": "37.1885571880",
		"REFINE_WGS84_LOGT": "127.7218894125",
		"DATA_STD_DE": "2020-08-18"
	},
	{
		"SIGUN_NM": "여주시",
		"CMPNM_NM": "농업회사법인자연애주식회사",
		"INDUTYPE_NM": "음료식품-농•축•수산품",
		"REFINE_ROADNM_ADDR": "경기도 여주시 점동면 장여로 735",
		"REFINE_LOTNO_ADDR": "경기도 여주시 점동면 덕평리 428-11번지",
		"TELNO": "",
		"REFINE_ZIPNO": "12667",
		"REFINE_WGS84_LAT": "37.1705649504",
		"REFINE_WGS84_LOGT": "127.6536322375",
		"DATA_STD_DE": "2020-08-18"
	},
	{
		"SIGUN_NM": "여주시",
		"CMPNM_NM": "농업회사법인주식회사영춘",
		"INDUTYPE_NM": "학원-기타 교육기관",
		"REFINE_ROADNM_ADDR": "경기도 여주시 점동면 가남로 1126-1",
		"REFINE_LOTNO_ADDR": "경기도 여주시 점동면 청안리 330번지",
		"TELNO": "",
		"REFINE_ZIPNO": "12667",
		"REFINE_WGS84_LAT": "37.2020300817",
		"REFINE_WGS84_LOGT": "127.6560962522",
		"DATA_STD_DE": "2020-08-18"
	},
	{
		"SIGUN_NM": "여주시",
		"CMPNM_NM": "누룽지도예",
		"INDUTYPE_NM": "문화.취미-민예•공예품",
		"REFINE_ROADNM_ADDR": "경기도 여주시 점동면 장여로 643-22",
		"REFINE_LOTNO_ADDR": "경기도 여주시 점동면 덕평리 572-17번지",
		"TELNO": "",
		"REFINE_ZIPNO": "12667",
		"REFINE_WGS84_LAT": "37.1667742220",
		"REFINE_WGS84_LOGT": "127.6430480297",
		"DATA_STD_DE": "2020-08-18"
	},
	{
		"SIGUN_NM": "여주시",
		"CMPNM_NM": "늘푸른가든",
		"INDUTYPE_NM": "일반휴게음식-일반한식",
		"REFINE_ROADNM_ADDR": "경기도 여주시 점동면 성주로 830",
		"REFINE_LOTNO_ADDR": "경기도 여주시 점동면 당진리 150-2번지",
		"TELNO": "",
		"REFINE_ZIPNO": "12668",
		"REFINE_WGS84_LAT": "37.1789069989",
		"REFINE_WGS84_LOGT": "127.6766643690",
		"DATA_STD_DE": "2020-08-18"
	},
	{
		"SIGUN_NM": "여주시",
		"CMPNM_NM": "능향골마을협동조합",
		"INDUTYPE_NM": "학원-기타 교육기관",
		"REFINE_ROADNM_ADDR": "경기도 여주시 점동면 사장골길 37-25",
		"REFINE_LOTNO_ADDR": "경기도 여주시 점동면 도리 산30-1번지",
		"TELNO": "",
		"REFINE_ZIPNO": "12665",
		"REFINE_WGS84_LAT": "37.2223992178",
		"REFINE_WGS84_LOGT": "127.6998956446",
		"DATA_STD_DE": "2020-08-18"
	},
	{
		"SIGUN_NM": "여주시",
		"CMPNM_NM": "다산불원보덕사",
		"INDUTYPE_NM": "보건위생-기타대인서비스",
		"REFINE_ROADNM_ADDR": "경기도 여주시 점동면 성주로 569",
		"REFINE_LOTNO_ADDR": "경기도 여주시 점동면 뇌곡리 245-1번지",
		"TELNO": "",
		"REFINE_ZIPNO": "12668",
		"REFINE_WGS84_LAT": "37.1614349608",
		"REFINE_WGS84_LOGT": "127.6594253743",
		"DATA_STD_DE": "2020-08-18"
	},
	{
		"SIGUN_NM": "여주시",
		"CMPNM_NM": "당진떡방앗간",
		"INDUTYPE_NM": "음료식품-제과점",
		"REFINE_ROADNM_ADDR": "경기도 여주시 점동면 밀머리길 3",
		"REFINE_LOTNO_ADDR": "경기도 여주시 점동면 당진리 251-5번지",
		"TELNO": "",
		"REFINE_ZIPNO": "12668",
		"REFINE_WGS84_LAT": "37.1834490270",
		"REFINE_WGS84_LOGT": "127.6833219376",
		"DATA_STD_DE": "2020-08-18"
	},
	{
		"SIGUN_NM": "여주시",
		"CMPNM_NM": "대동타이어",
		"INDUTYPE_NM": "자동차정비 유지-자동차시트•타이어",
		"REFINE_ROADNM_ADDR": "경기도 여주시 점동면 청안로 196",
		"REFINE_LOTNO_ADDR": "경기도 여주시 점동면 처리 583번지",
		"TELNO": "",
		"REFINE_ZIPNO": "12666",
		"REFINE_WGS84_LAT": "37.2114017342",
		"REFINE_WGS84_LOGT": "127.6649739669",
		"DATA_STD_DE": "2020-08-18"
	},
	{
		"SIGUN_NM": "여주시",
		"CMPNM_NM": "도리마트",
		"INDUTYPE_NM": "유통업 영리-슈퍼마켓",
		"REFINE_ROADNM_ADDR": "경기도 여주시 점동면 도리길 113-8",
		"REFINE_LOTNO_ADDR": "경기도 여주시 점동면 도리 188번지",
		"TELNO": "",
		"REFINE_ZIPNO": "12665",
		"REFINE_WGS84_LAT": "37.2215547508",
		"REFINE_WGS84_LOGT": "127.7035116468",
		"DATA_STD_DE": "2020-08-18"
	},
	{
		"SIGUN_NM": "여주시",
		"CMPNM_NM": "도리수상레져",
		"INDUTYPE_NM": "레저업소-기타레져업소",
		"REFINE_ROADNM_ADDR": "",
		"REFINE_LOTNO_ADDR": "경기도 여주시 점동면 도리 379 (131번지선)",
		"TELNO": "",
		"REFINE_ZIPNO": "12665",
		"REFINE_WGS84_LAT": "37.2274477448",
		"REFINE_WGS84_LOGT": "127.7121285109",
		"DATA_STD_DE": "2020-08-18"
	},
	{
		"SIGUN_NM": "여주시",
		"CMPNM_NM": "돈촌유전자",
		"INDUTYPE_NM": "농업-기타농업관련",
		"REFINE_ROADNM_ADDR": "경기도 여주시 점동면 성주로 494",
		"REFINE_LOTNO_ADDR": "경기도 여주시 점동면 뇌곡리 321-1",
		"TELNO": "",
		"REFINE_ZIPNO": "12668",
		"REFINE_WGS84_LAT": "37.1556082319",
		"REFINE_WGS84_LOGT": "127.6553250490",
		"DATA_STD_DE": "2020-08-18"
	},
	{
		"SIGUN_NM": "여주시",
		"CMPNM_NM": "돈촌유전자",
		"INDUTYPE_NM": "농업-기타농업관련",
		"REFINE_ROADNM_ADDR": "경기도 여주시 점동면 성주로 494",
		"REFINE_LOTNO_ADDR": "경기도 여주시 점동면 뇌곡리 321-1",
		"TELNO": "",
		"REFINE_ZIPNO": "12668",
		"REFINE_WGS84_LAT": "37.1556082319",
		"REFINE_WGS84_LOGT": "127.6553250490",
		"DATA_STD_DE": "2020-08-18"
	},
	{
		"SIGUN_NM": "여주시",
		"CMPNM_NM": "돌쇠출장세차이천점",
		"INDUTYPE_NM": "자동차정비 유지-세차장",
		"REFINE_ROADNM_ADDR": "경기도 여주시 점동면 어우실길 6-2",
		"REFINE_LOTNO_ADDR": "경기도 여주시 점동면 관한리 393-10번지",
		"TELNO": "",
		"REFINE_ZIPNO": "12668",
		"REFINE_WGS84_LAT": "37.1531338611",
		"REFINE_WGS84_LOGT": "127.6518288945",
		"DATA_STD_DE": "2020-08-18"
	},
	{
		"SIGUN_NM": "여주시",
		"CMPNM_NM": "동광산업",
		"INDUTYPE_NM": "유통업 영리-기타유통업",
		"REFINE_ROADNM_ADDR": "경기도 여주시 점동면 장여로 1342-32",
		"REFINE_LOTNO_ADDR": "경기도 여주시 점동면 처리 536",
		"TELNO": "",
		"REFINE_ZIPNO": "12666",
		"REFINE_WGS84_LAT": "37.2188406303",
		"REFINE_WGS84_LOGT": "127.6697466747",
		"DATA_STD_DE": "2020-08-18"
	},
	{
		"SIGUN_NM": "여주시",
		"CMPNM_NM": "동원통종닭",
		"INDUTYPE_NM": "일반휴게음식-일반한식",
		"REFINE_ROADNM_ADDR": "경기도 여주시 점동면 가래울길 25",
		"REFINE_LOTNO_ADDR": "경기도 여주시 점동면 사곡리 371번지 1층",
		"TELNO": "",
		"REFINE_ZIPNO": "12665",
		"REFINE_WGS84_LAT": "37.2054465345",
		"REFINE_WGS84_LOGT": "127.6753513500",
		"DATA_STD_DE": "2020-08-18"
	},
	{
		"SIGUN_NM": "여주시",
		"CMPNM_NM": "디아(dia)",
		"INDUTYPE_NM": "일반휴게음식-서양음식",
		"REFINE_ROADNM_ADDR": "경기도 여주시 점동면 점동로 574-83",
		"REFINE_LOTNO_ADDR": "경기도 여주시 점동면 장안리 265번지 1층",
		"TELNO": "",
		"REFINE_ZIPNO": "12665",
		"REFINE_WGS84_LAT": "37.1953900625",
		"REFINE_WGS84_LOGT": "127.7169290169",
		"DATA_STD_DE": "2020-08-18"
	},
	{
		"SIGUN_NM": "여주시",
		"CMPNM_NM": "러브레터(점동점)",
		"INDUTYPE_NM": "일반휴게음식-주점",
		"REFINE_ROADNM_ADDR": "경기도 여주시 점동면 청안리길 9",
		"REFINE_LOTNO_ADDR": "경기도 여주시 점동면 청안리 145-3번지",
		"TELNO": "",
		"REFINE_ZIPNO": "12667",
		"REFINE_WGS84_LAT": "37.2065572983",
		"REFINE_WGS84_LOGT": "127.6612332091",
		"DATA_STD_DE": "2020-08-18"
	},
	{
		"SIGUN_NM": "여주시",
		"CMPNM_NM": "로그인 여주점동점",
		"INDUTYPE_NM": "유통업 영리-편 의 점",
		"REFINE_ROADNM_ADDR": "경기도 여주시 점동면 장여로 899",
		"REFINE_LOTNO_ADDR": "경기도 여주시 점동면 덕평리 166-2번지",
		"TELNO": "",
		"REFINE_ZIPNO": "12667",
		"REFINE_WGS84_LAT": "37.1809639768",
		"REFINE_WGS84_LOGT": "127.6628573886",
		"DATA_STD_DE": "2020-08-18"
	},
	{
		"SIGUN_NM": "여주시",
		"CMPNM_NM": "마음대로식당",
		"INDUTYPE_NM": "일반휴게음식-일반한식",
		"REFINE_ROADNM_ADDR": "경기도 여주시 점동면 청안로 143",
		"REFINE_LOTNO_ADDR": "경기도 여주시 점동면 청안리 159-6번지",
		"TELNO": "",
		"REFINE_ZIPNO": "12667",
		"REFINE_WGS84_LAT": "37.2072492244",
		"REFINE_WGS84_LOGT": "127.6628124288",
		"DATA_STD_DE": "2020-08-18"
	},
	{
		"SIGUN_NM": "여주시",
		"CMPNM_NM": "만남",
		"INDUTYPE_NM": "일반휴게음식-일반한식",
		"REFINE_ROADNM_ADDR": "경기도 여주시 점동면 청안리길 9",
		"REFINE_LOTNO_ADDR": "경기도 여주시 점동면 청안리 145-3번지",
		"TELNO": "",
		"REFINE_ZIPNO": "12667",
		"REFINE_WGS84_LAT": "37.2065572983",
		"REFINE_WGS84_LOGT": "127.6612332091",
		"DATA_STD_DE": "2020-08-18"
	},
	{
		"SIGUN_NM": "여주시",
		"CMPNM_NM": "메탈 시스템",
		"INDUTYPE_NM": "주방용구-주방용구",
		"REFINE_ROADNM_ADDR": "경기도 여주시 점동면 장여로 1049-10",
		"REFINE_LOTNO_ADDR": "경기도 여주시 점동면 청안리 35-5번지",
		"TELNO": "",
		"REFINE_ZIPNO": "12667",
		"REFINE_WGS84_LAT": "37.1950818732",
		"REFINE_WGS84_LOGT": "127.6615693734",
		"DATA_STD_DE": "2020-08-18"
	},
	{
		"SIGUN_NM": "여주시",
		"CMPNM_NM": "명주한정식",
		"INDUTYPE_NM": "일반휴게음식-일반한식",
		"REFINE_ROADNM_ADDR": "경기도 여주시 점동면 점동로 223",
		"REFINE_LOTNO_ADDR": "경기도 여주시 점동면 사곡리 165-5번지",
		"TELNO": "",
		"REFINE_ZIPNO": "12665",
		"REFINE_WGS84_LAT": "37.2031719931",
		"REFINE_WGS84_LOGT": "127.6832794756",
		"DATA_STD_DE": "2020-08-18"
	},
	{
		"SIGUN_NM": "여주시",
		"CMPNM_NM": "문소연",
		"INDUTYPE_NM": "보건위생-미용원",
		"REFINE_ROADNM_ADDR": "경기도 여주시 점동면 청안리길 9",
		"REFINE_LOTNO_ADDR": "경기도 여주시 점동면 청안리 145-3번지 1층 104호",
		"TELNO": "",
		"REFINE_ZIPNO": "12667",
		"REFINE_WGS84_LAT": "37.2065572983",
		"REFINE_WGS84_LOGT": "127.6612332091",
		"DATA_STD_DE": "2020-08-18"
	},
	{
		"SIGUN_NM": "여주시",
		"CMPNM_NM": "미니스톱 여주점동점",
		"INDUTYPE_NM": "유통업 영리-편 의 점",
		"REFINE_ROADNM_ADDR": "경기도 여주시 점동면 청안로 158",
		"REFINE_LOTNO_ADDR": "경기도 여주시 점동면 청안리 164번지",
		"TELNO": "",
		"REFINE_ZIPNO": "12667",
		"REFINE_WGS84_LAT": "37.2080584686",
		"REFINE_WGS84_LOGT": "127.6642792342",
		"DATA_STD_DE": "2020-08-18"
	},
	{
		"SIGUN_NM": "여주시",
		"CMPNM_NM": "미식가",
		"INDUTYPE_NM": "일반휴게음식-일반한식",
		"REFINE_ROADNM_ADDR": "경기도 여주시 점동면 장여로 621-1",
		"REFINE_LOTNO_ADDR": "경기도 여주시 점동면 덕평리 578-10번지",
		"TELNO": "",
		"REFINE_ZIPNO": "12667",
		"REFINE_WGS84_LAT": "37.1654587535",
		"REFINE_WGS84_LOGT": "127.6425499599",
		"DATA_STD_DE": "2020-08-18"
	},
	{
		"SIGUN_NM": "여주시",
		"CMPNM_NM": "밀머리농어촌체험휴양마을",
		"INDUTYPE_NM": "학원-기타 교육기관",
		"REFINE_ROADNM_ADDR": "경기도 여주시 점동면 밀머리길 20",
		"REFINE_LOTNO_ADDR": "경기도 여주시 점동면 당진리 334-3번지",
		"TELNO": "",
		"REFINE_ZIPNO": "12668",
		"REFINE_WGS84_LAT": "37.1824396041",
		"REFINE_WGS84_LOGT": "127.6832181046",
		"DATA_STD_DE": "2020-08-18"
	},
	{
		"SIGUN_NM": "여주시",
		"CMPNM_NM": "밀머리마을협동조합",
		"INDUTYPE_NM": "학원-기타 교육기관",
		"REFINE_ROADNM_ADDR": "경기도 여주시 점동면 밀머리길 20",
		"REFINE_LOTNO_ADDR": "경기도 여주시 점동면 당진리 334-3번지",
		"TELNO": "",
		"REFINE_ZIPNO": "12668",
		"REFINE_WGS84_LAT": "37.1824396041",
		"REFINE_WGS84_LOGT": "127.6832181046",
		"DATA_STD_DE": "2020-08-18"
	},
	{
		"SIGUN_NM": "여주시",
		"CMPNM_NM": "밥푸는집",
		"INDUTYPE_NM": "일반휴게음식-일반한식",
		"REFINE_ROADNM_ADDR": "경기도 여주시 점동면 청안로 192-1",
		"REFINE_LOTNO_ADDR": "경기도 여주시 점동면 처리 583-6번지",
		"TELNO": "",
		"REFINE_ZIPNO": "12666",
		"REFINE_WGS84_LAT": "37.2110864927",
		"REFINE_WGS84_LOGT": "127.6647929574",
		"DATA_STD_DE": "2020-08-18"
	},
	{
		"SIGUN_NM": "여주시",
		"CMPNM_NM": "방촌묵집",
		"INDUTYPE_NM": "일반휴게음식-일반한식",
		"REFINE_ROADNM_ADDR": "경기도 여주시 점동면 장여로 1023",
		"REFINE_LOTNO_ADDR": "경기도 여주시 점동면 덕평리 2-4번지",
		"TELNO": "",
		"REFINE_ZIPNO": "12667",
		"REFINE_WGS84_LAT": "37.1921970387",
		"REFINE_WGS84_LOGT": "127.6617998416",
		"DATA_STD_DE": "2020-08-18"
	},
	{
		"SIGUN_NM": "여주시",
		"CMPNM_NM": "백두슈퍼",
		"INDUTYPE_NM": "유통업 영리-슈퍼마켓",
		"REFINE_ROADNM_ADDR": "경기도 여주시 점동면 원부로 38",
		"REFINE_LOTNO_ADDR": "경기도 여주시 점동면 원부리 262번지 1층",
		"TELNO": "",
		"REFINE_ZIPNO": "12668",
		"REFINE_WGS84_LAT": "37.1604643615",
		"REFINE_WGS84_LOGT": "127.6353212034",
		"DATA_STD_DE": "2020-08-18"
	},
	{
		"SIGUN_NM": "여주시",
		"CMPNM_NM": "벤치",
		"INDUTYPE_NM": "일반휴게음식-일반한식",
		"REFINE_ROADNM_ADDR": "경기도 여주시 점동면 청안로 135",
		"REFINE_LOTNO_ADDR": "경기도 여주시 점동면 청안리 604-36번지",
		"TELNO": "",
		"REFINE_ZIPNO": "12667",
		"REFINE_WGS84_LAT": "37.2066279180",
		"REFINE_WGS84_LOGT": "127.6623265041",
		"DATA_STD_DE": "2020-08-18"
	},
	{
		"SIGUN_NM": "여주시",
		"CMPNM_NM": "보광식당",
		"INDUTYPE_NM": "일반휴게음식-일반한식",
		"REFINE_ROADNM_ADDR": "경기도 여주시 점동면 청안리길 5",
		"REFINE_LOTNO_ADDR": "경기도 여주시 점동면 청안리 155-4번지",
		"TELNO": "",
		"REFINE_ZIPNO": "12667",
		"REFINE_WGS84_LAT": "37.2064125202",
		"REFINE_WGS84_LOGT": "127.6616386032",
		"DATA_STD_DE": "2020-08-18"
	},
	{
		"SIGUN_NM": "여주시",
		"CMPNM_NM": "봉명건설조경",
		"INDUTYPE_NM": "건축자재-인테리어전문",
		"REFINE_ROADNM_ADDR": "경기도 여주시 점동면 청안로 130-8",
		"REFINE_LOTNO_ADDR": "경기도 여주시 점동면 청안리 130-9번지",
		"TELNO": "",
		"REFINE_ZIPNO": "12667",
		"REFINE_WGS84_LAT": "37.2056361066",
		"REFINE_WGS84_LOGT": "127.6625159594",
		"DATA_STD_DE": "2020-08-18"
	},
	{
		"SIGUN_NM": "여주시",
		"CMPNM_NM": "부뚜막",
		"INDUTYPE_NM": "일반휴게음식-일반한식",
		"REFINE_ROADNM_ADDR": "경기도 여주시 점동면 청안리길 9",
		"REFINE_LOTNO_ADDR": "경기도 여주시 점동면 청안리 145-3번지",
		"TELNO": "",
		"REFINE_ZIPNO": "12667",
		"REFINE_WGS84_LAT": "37.2065572983",
		"REFINE_WGS84_LOGT": "127.6612332091",
		"DATA_STD_DE": "2020-08-18"
	},
	{
		"SIGUN_NM": "여주시",
		"CMPNM_NM": "블랙마운틴",
		"INDUTYPE_NM": "문화.취미-화랑",
		"REFINE_ROADNM_ADDR": "경기도 여주시 점동면 덕실길 31-99",
		"REFINE_LOTNO_ADDR": "경기도 여주시 점동면 덕평리 355번지",
		"TELNO": "",
		"REFINE_ZIPNO": "12667",
		"REFINE_WGS84_LAT": "37.1784064396",
		"REFINE_WGS84_LOGT": "127.6542677091",
		"DATA_STD_DE": "2020-08-18"
	},
	{
		"SIGUN_NM": "여주시",
		"CMPNM_NM": "삼돌네",
		"INDUTYPE_NM": "일반휴게음식-일반한식",
		"REFINE_ROADNM_ADDR": "경기도 여주시 점동면 선사길 311-9",
		"REFINE_LOTNO_ADDR": "경기도 여주시 점동면 흔암리 111-3번지 3동 1층",
		"TELNO": "",
		"REFINE_ZIPNO": "12666",
		"REFINE_WGS84_LAT": "37.2391658997",
		"REFINE_WGS84_LOGT": "127.6828366909",
		"DATA_STD_DE": "2020-08-18"
	},
	{
		"SIGUN_NM": "여주시",
		"CMPNM_NM": "삼성문구",
		"INDUTYPE_NM": "서적문구-문구용품",
		"REFINE_ROADNM_ADDR": "",
		"REFINE_LOTNO_ADDR": "경기도 여주시 점동면 청안리 123",
		"TELNO": "",
		"REFINE_ZIPNO": "12667",
		"REFINE_WGS84_LAT": "",
		"REFINE_WGS84_LOGT": "",
		"DATA_STD_DE": "2020-08-18"
	},
	{
		"SIGUN_NM": "여주시",
		"CMPNM_NM": "삼신석재",
		"INDUTYPE_NM": "건축자재-기타건축자재",
		"REFINE_ROADNM_ADDR": "경기도 여주시 점동면 청안로 191",
		"REFINE_LOTNO_ADDR": "경기도 여주시 점동면 처리 584-1번지",
		"TELNO": "",
		"REFINE_ZIPNO": "12666",
		"REFINE_WGS84_LAT": "37.2113309519",
		"REFINE_WGS84_LOGT": "127.6640158430",
		"DATA_STD_DE": "2020-08-18"
	},
	{
		"SIGUN_NM": "여주시",
		"CMPNM_NM": "삼합낚시터",
		"INDUTYPE_NM": "레저업소-기타레져업소",
		"REFINE_ROADNM_ADDR": "경기도 여주시 점동면 점동로 650",
		"REFINE_LOTNO_ADDR": "경기도 여주시 점동면 삼합리 551-2번지",
		"TELNO": "",
		"REFINE_ZIPNO": "12665",
		"REFINE_WGS84_LAT": "37.1998425505",
		"REFINE_WGS84_LOGT": "127.7268129754",
		"DATA_STD_DE": "2020-08-18"
	},
	{
		"SIGUN_NM": "여주시",
		"CMPNM_NM": "삼호종합건재",
		"INDUTYPE_NM": "건축자재-목재•석재•철물",
		"REFINE_ROADNM_ADDR": "경기도 여주시 점동면 청안로 158",
		"REFINE_LOTNO_ADDR": "경기도 여주시 점동면 청안리 164번지",
		"TELNO": "",
		"REFINE_ZIPNO": "12667",
		"REFINE_WGS84_LAT": "37.2080584686",
		"REFINE_WGS84_LOGT": "127.6642792342",
		"DATA_STD_DE": "2020-08-18"
	},
	{
		"SIGUN_NM": "여주시",
		"CMPNM_NM": "서가한의원",
		"INDUTYPE_NM": "의원-한의원",
		"REFINE_ROADNM_ADDR": "경기도 여주시 점동면 청안로 139",
		"REFINE_LOTNO_ADDR": "경기도 여주시 점동면 청안리 154-4번지",
		"TELNO": "",
		"REFINE_ZIPNO": "12667",
		"REFINE_WGS84_LAT": "37.2068804357",
		"REFINE_WGS84_LOGT": "127.6622368884",
		"DATA_STD_DE": "2020-08-18"
	},
	{
		"SIGUN_NM": "여주시",
		"CMPNM_NM": "서향 점동점",
		"INDUTYPE_NM": "일반휴게음식-중국식",
		"REFINE_ROADNM_ADDR": "경기도 여주시 점동면 청안로 139",
		"REFINE_LOTNO_ADDR": "경기도 여주시 점동면 청안리 154-4번지 1층",
		"TELNO": "",
		"REFINE_ZIPNO": "12667",
		"REFINE_WGS84_LAT": "37.2068804357",
		"REFINE_WGS84_LOGT": "127.6622368884",
		"DATA_STD_DE": "2020-08-18"
	},
	{
		"SIGUN_NM": "여주시",
		"CMPNM_NM": "선진사운드",
		"INDUTYPE_NM": "전기제품-가전제품",
		"REFINE_ROADNM_ADDR": "경기도 여주시 점동면 장여로 589-10",
		"REFINE_LOTNO_ADDR": "경기도 여주시 점동면 원부리 145번지",
		"TELNO": "",
		"REFINE_ZIPNO": "12667",
		"REFINE_WGS84_LAT": "37.1648679681",
		"REFINE_WGS84_LOGT": "127.6390572172",
		"DATA_STD_DE": "2020-08-18"
	},
	{
		"SIGUN_NM": "여주시",
		"CMPNM_NM": "성림농원",
		"INDUTYPE_NM": "문화.취미-화원",
		"REFINE_ROADNM_ADDR": "",
		"REFINE_LOTNO_ADDR": "경기도 여주시 점동면 덕평리 산27-9",
		"TELNO": "",
		"REFINE_ZIPNO": "12667",
		"REFINE_WGS84_LAT": "37.1785339004",
		"REFINE_WGS84_LOGT": "127.6503013052",
		"DATA_STD_DE": "2020-08-18"
	},
	{
		"SIGUN_NM": "여주시",
		"CMPNM_NM": "성문농장 농업회사법인 유한회사",
		"INDUTYPE_NM": "음료식품-기타음료식품",
		"REFINE_ROADNM_ADDR": "경기도 여주시 점동면 청안리길 57-9",
		"REFINE_LOTNO_ADDR": "경기도 여주시 점동면 청안리 250-2번지",
		"TELNO": "",
		"REFINE_ZIPNO": "12667",
		"REFINE_WGS84_LAT": "37.2047694859",
		"REFINE_WGS84_LOGT": "127.6567667800",
		"DATA_STD_DE": "2020-08-18"
	},
	{
		"SIGUN_NM": "여주시",
		"CMPNM_NM": "성산여주쌀밥",
		"INDUTYPE_NM": "일반휴게음식-일반한식",
		"REFINE_ROADNM_ADDR": "경기도 여주시 점동면 장여로 585",
		"REFINE_LOTNO_ADDR": "경기도 여주시 점동면 원부리 201-1번지",
		"TELNO": "",
		"REFINE_ZIPNO": "12667",
		"REFINE_WGS84_LAT": "37.1642913661",
		"REFINE_WGS84_LOGT": "127.6387971061",
		"DATA_STD_DE": "2020-08-18"
	},
	{
		"SIGUN_NM": "여주시",
		"CMPNM_NM": "성신농산",
		"INDUTYPE_NM": "음료식품-미곡상",
		"REFINE_ROADNM_ADDR": "경기도 여주시 점동면 성주로 658",
		"REFINE_LOTNO_ADDR": "경기도 여주시 점동면 성신리 226-15번지",
		"TELNO": "",
		"REFINE_ZIPNO": "12668",
		"REFINE_WGS84_LAT": "37.1661392986",
		"REFINE_WGS84_LOGT": "127.6667452785",
		"DATA_STD_DE": "2020-08-18"
	},
	{
		"SIGUN_NM": "여주시",
		"CMPNM_NM": "세규산업 주식회사",
		"INDUTYPE_NM": "용역 서비스-기타용역서비스",
		"REFINE_ROADNM_ADDR": "경기도 여주시 점동면 청안로 154-3",
		"REFINE_LOTNO_ADDR": "경기도 여주시 점동면 청안리 163-13번지",
		"TELNO": "",
		"REFINE_ZIPNO": "12667",
		"REFINE_WGS84_LAT": "37.2072384844",
		"REFINE_WGS84_LOGT": "127.6640633339",
		"DATA_STD_DE": "2020-08-18"
	},
	{
		"SIGUN_NM": "여주시",
		"CMPNM_NM": "세영농원",
		"INDUTYPE_NM": "음료식품-농•축•수산품",
		"REFINE_ROADNM_ADDR": "경기도 여주시 점동면 성주로 1020-18",
		"REFINE_LOTNO_ADDR": "경기도 여주시 점동면 현수리 189-3번지",
		"TELNO": "",
		"REFINE_ZIPNO": "12668",
		"REFINE_WGS84_LAT": "37.1867817191",
		"REFINE_WGS84_LOGT": "127.6906420029",
		"DATA_STD_DE": "2020-08-18"
	},
	{
		"SIGUN_NM": "여주시",
		"CMPNM_NM": "소나무집바람난오리",
		"INDUTYPE_NM": "일반휴게음식-일반한식",
		"REFINE_ROADNM_ADDR": "경기도 여주시 점동면 점동로 341",
		"REFINE_LOTNO_ADDR": "경기도 여주시 점동면 사곡리 85-4번지",
		"TELNO": "",
		"REFINE_ZIPNO": "12665",
		"REFINE_WGS84_LAT": "37.2014583394",
		"REFINE_WGS84_LOGT": "127.6951751430",
		"DATA_STD_DE": "2020-08-18"
	},
	{
		"SIGUN_NM": "여주시",
		"CMPNM_NM": "솔밭촌",
		"INDUTYPE_NM": "일반휴게음식-일반한식",
		"REFINE_ROADNM_ADDR": "경기도 여주시 점동면 장여로 825",
		"REFINE_LOTNO_ADDR": "경기도 여주시 점동면 덕평리 283-1번지",
		"TELNO": "",
		"REFINE_ZIPNO": "12667",
		"REFINE_WGS84_LAT": "37.1753322309",
		"REFINE_WGS84_LOGT": "127.6613245406",
		"DATA_STD_DE": "2020-08-18"
	},
	{
		"SIGUN_NM": "여주시",
		"CMPNM_NM": "수상스키아케데미(Waterski Academy)",
		"INDUTYPE_NM": "레저업소-기타레져업소",
		"REFINE_ROADNM_ADDR": "",
		"REFINE_LOTNO_ADDR": "경기도 여주시 점동면 도리 379번지",
		"TELNO": "",
		"REFINE_ZIPNO": "12665",
		"REFINE_WGS84_LAT": "37.2274477448",
		"REFINE_WGS84_LOGT": "127.7121285109",
		"DATA_STD_DE": "2020-08-18"
	},
	{
		"SIGUN_NM": "여주시",
		"CMPNM_NM": "수정건강원",
		"INDUTYPE_NM": "건강식품-기타건강식품",
		"REFINE_ROADNM_ADDR": "경기도 여주시 점동면 장여로 1335",
		"REFINE_LOTNO_ADDR": "경기도 여주시 점동면 처리 520-6번지 나동 1층",
		"TELNO": "",
		"REFINE_ZIPNO": "12666",
		"REFINE_WGS84_LAT": "37.2191250853",
		"REFINE_WGS84_LOGT": "127.6662080952",
		"DATA_STD_DE": "2020-08-18"
	},
	{
		"SIGUN_NM": "여주시",
		"CMPNM_NM": "술이야",
		"INDUTYPE_NM": "일반휴게음식-주점",
		"REFINE_ROADNM_ADDR": "경기도 여주시 점동면 청안로 129",
		"REFINE_LOTNO_ADDR": "경기도 여주시 점동면 청안리 126-4번지",
		"TELNO": "",
		"REFINE_ZIPNO": "12667",
		"REFINE_WGS84_LAT": "37.2061416822",
		"REFINE_WGS84_LOGT": "127.6619423010",
		"DATA_STD_DE": "2020-08-18"
	},
	{
		"SIGUN_NM": "여주시",
		"CMPNM_NM": "스마트노래연습장",
		"INDUTYPE_NM": "레저업소-노 래 방",
		"REFINE_ROADNM_ADDR": "경기도 여주시 점동면 청안로 172",
		"REFINE_LOTNO_ADDR": "경기도 여주시 점동면 청안리 166-19번지 2층",
		"TELNO": "",
		"REFINE_ZIPNO": "12667",
		"REFINE_WGS84_LAT": "37.2095724107",
		"REFINE_WGS84_LOGT": "127.6645868054",
		"DATA_STD_DE": "2020-08-18"
	},
	{
		"SIGUN_NM": "여주시",
		"CMPNM_NM": "씨유여주점동점",
		"INDUTYPE_NM": "유통업 영리-편 의 점",
		"REFINE_ROADNM_ADDR": "경기도 여주시 점동면 청안리길 2",
		"REFINE_LOTNO_ADDR": "경기도 여주시 점동면 청안리 125-1번지",
		"TELNO": "",
		"REFINE_ZIPNO": "12667",
		"REFINE_WGS84_LAT": "37.2065829866",
		"REFINE_WGS84_LOGT": "127.6622249821",
		"DATA_STD_DE": "2020-08-18"
	},
	{
		"SIGUN_NM": "여주시",
		"CMPNM_NM": "알뜰공판장",
		"INDUTYPE_NM": "유통업 영리-슈퍼마켓",
		"REFINE_ROADNM_ADDR": "경기도 여주시 점동면 청안리길 5",
		"REFINE_LOTNO_ADDR": "경기도 여주시 점동면 청안리 155-4번지",
		"TELNO": "",
		"REFINE_ZIPNO": "12667",
		"REFINE_WGS84_LAT": "37.2064125202",
		"REFINE_WGS84_LOGT": "127.6616386032",
		"DATA_STD_DE": "2020-08-18"
	},
	{
		"SIGUN_NM": "여주시",
		"CMPNM_NM": "앵콜노래연습장",
		"INDUTYPE_NM": "레저업소-노 래 방",
		"REFINE_ROADNM_ADDR": "경기도 여주시 점동면 청안로 130-2",
		"REFINE_LOTNO_ADDR": "경기도 여주시 점동면 청안리 130-3번지",
		"TELNO": "",
		"REFINE_ZIPNO": "12667",
		"REFINE_WGS84_LAT": "37.2059070387",
		"REFINE_WGS84_LOGT": "127.6621446493",
		"DATA_STD_DE": "2020-08-18"
	},
	{
		"SIGUN_NM": "여주시",
		"CMPNM_NM": "약수농원",
		"INDUTYPE_NM": "음료식품-농•축•수산품",
		"REFINE_ROADNM_ADDR": "경기도 여주시 점동면 우뢰실길 59-73",
		"REFINE_LOTNO_ADDR": "경기도 여주시 점동면 뇌곡리 44번지",
		"TELNO": "",
		"REFINE_ZIPNO": "12668",
		"REFINE_WGS84_LAT": "37.1568111269",
		"REFINE_WGS84_LOGT": "127.6656774118",
		"DATA_STD_DE": "2020-08-18"
	},
	{
		"SIGUN_NM": "여주시",
		"CMPNM_NM": "양귀비까페",
		"INDUTYPE_NM": "일반휴게음식-서양음식",
		"REFINE_ROADNM_ADDR": "경기도 여주시 점동면 청안로 172",
		"REFINE_LOTNO_ADDR": "경기도 여주시 점동면 청안리 166-19번지 1층",
		"TELNO": "",
		"REFINE_ZIPNO": "12667",
		"REFINE_WGS84_LAT": "37.2095724107",
		"REFINE_WGS84_LOGT": "127.6645868054",
		"DATA_STD_DE": "2020-08-18"
	},
	{
		"SIGUN_NM": "여주시",
		"CMPNM_NM": "양귀비카페",
		"INDUTYPE_NM": "일반휴게음식-서양음식",
		"REFINE_ROADNM_ADDR": "경기도 여주시 점동면 청안로 172",
		"REFINE_LOTNO_ADDR": "경기도 여주시 점동면 청안리 166-19번지",
		"TELNO": "",
		"REFINE_ZIPNO": "12667",
		"REFINE_WGS84_LAT": "37.2095724107",
		"REFINE_WGS84_LOGT": "127.6645868054",
		"DATA_STD_DE": "2020-08-18"
	},
	{
		"SIGUN_NM": "여주시",
		"CMPNM_NM": "어우실 낚시터",
		"INDUTYPE_NM": "레저업소-기타레져업소",
		"REFINE_ROADNM_ADDR": "경기도 여주시 점동면 어우실길 65",
		"REFINE_LOTNO_ADDR": "경기도 여주시 점동면 관한리 418번지",
		"TELNO": "",
		"REFINE_ZIPNO": "12668",
		"REFINE_WGS84_LAT": "37.1519360003",
		"REFINE_WGS84_LOGT": "127.6579414466",
		"DATA_STD_DE": "2020-08-18"
	},
	{
		"SIGUN_NM": "여주시",
		"CMPNM_NM": "어우실가든",
		"INDUTYPE_NM": "일반휴게음식-일반한식",
		"REFINE_ROADNM_ADDR": "경기도 여주시 점동면 어우실길 65",
		"REFINE_LOTNO_ADDR": "경기도 여주시 점동면 관한리 418번지",
		"TELNO": "",
		"REFINE_ZIPNO": "12668",
		"REFINE_WGS84_LAT": "37.1519360003",
		"REFINE_WGS84_LOGT": "127.6579414466",
		"DATA_STD_DE": "2020-08-18"
	},
	{
		"SIGUN_NM": "여주시",
		"CMPNM_NM": "어제오늘내일",
		"INDUTYPE_NM": "문화.취미-민예•공예품",
		"REFINE_ROADNM_ADDR": "경기도 여주시 점동면 청안로 243-3",
		"REFINE_LOTNO_ADDR": "경기도 여주시 점동면 처리 553번지",
		"TELNO": "",
		"REFINE_ZIPNO": "12666",
		"REFINE_WGS84_LAT": "37.2151861304",
		"REFINE_WGS84_LOGT": "127.6660642041",
		"DATA_STD_DE": "2020-08-18"
	},
	{
		"SIGUN_NM": "여주시",
		"CMPNM_NM": "엄지알뜰가전",
		"INDUTYPE_NM": "전기제품-가전제품",
		"REFINE_ROADNM_ADDR": "경기도 여주시 점동면 장여로 899",
		"REFINE_LOTNO_ADDR": "경기도 여주시 점동면 덕평리 166-2번지",
		"TELNO": "",
		"REFINE_ZIPNO": "12667",
		"REFINE_WGS84_LAT": "37.1809639768",
		"REFINE_WGS84_LOGT": "127.6628573886",
		"DATA_STD_DE": "2020-08-18"
	},
	{
		"SIGUN_NM": "여주시",
		"CMPNM_NM": "엔엘에스 주식회사",
		"INDUTYPE_NM": "건축자재-기타건축자재",
		"REFINE_ROADNM_ADDR": "경기도 여주시 점동면 청안로 156-11",
		"REFINE_LOTNO_ADDR": "경기도 여주시 점동면 청안리 163-9번지",
		"TELNO": "",
		"REFINE_ZIPNO": "12667",
		"REFINE_WGS84_LAT": "37.2076513299",
		"REFINE_WGS84_LOGT": "127.6653602414",
		"DATA_STD_DE": "2020-08-18"
	},
	{
		"SIGUN_NM": "여주시",
		"CMPNM_NM": "여주참숯가마식당",
		"INDUTYPE_NM": "일반휴게음식-일반한식",
		"REFINE_ROADNM_ADDR": "경기도 여주시 점동면 장여로 1049-28",
		"REFINE_LOTNO_ADDR": "경기도 여주시 점동면 청안리 37번지",
		"TELNO": "",
		"REFINE_ZIPNO": "12667",
		"REFINE_WGS84_LAT": "37.1962355237",
		"REFINE_WGS84_LOGT": "127.6616845117",
		"DATA_STD_DE": "2020-08-18"
	},
	{
		"SIGUN_NM": "여주시",
		"CMPNM_NM": "여흥회관",
		"INDUTYPE_NM": "일반휴게음식-일반한식",
		"REFINE_ROADNM_ADDR": "경기도 여주시 점동면 청안리길 4",
		"REFINE_LOTNO_ADDR": "경기도 여주시 점동면 청안리 156-4번지",
		"TELNO": "",
		"REFINE_ZIPNO": "12667",
		"REFINE_WGS84_LAT": "37.2067093996",
		"REFINE_WGS84_LOGT": "127.6620674791",
		"DATA_STD_DE": "2020-08-18"
	},
	{
		"SIGUN_NM": "여주시",
		"CMPNM_NM": "예목공방",
		"INDUTYPE_NM": "문화.취미-문화취미기타",
		"REFINE_ROADNM_ADDR": "경기도 여주시 점동면 청안로 101",
		"REFINE_LOTNO_ADDR": "경기도 여주시 점동면 청안리 110번지",
		"TELNO": "",
		"REFINE_ZIPNO": "12667",
		"REFINE_WGS84_LAT": "37.2033853362",
		"REFINE_WGS84_LOGT": "127.6604939733",
		"DATA_STD_DE": "2020-08-18"
	},
	{
		"SIGUN_NM": "여주시",
		"CMPNM_NM": "예터",
		"INDUTYPE_NM": "숙박업-여관/기타숙박업",
		"REFINE_ROADNM_ADDR": "경기도 여주시 점동면 오갑산길 148-124",
		"REFINE_LOTNO_ADDR": "경기도 여주시 점동면 당진리 7-3번지",
		"TELNO": "",
		"REFINE_ZIPNO": "12668",
		"REFINE_WGS84_LAT": "37.1645971550",
		"REFINE_WGS84_LOGT": "127.6911043808",
		"DATA_STD_DE": "2020-08-18"
	},
	{
		"SIGUN_NM": "여주시",
		"CMPNM_NM": "옛맛시골집",
		"INDUTYPE_NM": "일반휴게음식-일반한식",
		"REFINE_ROADNM_ADDR": "경기도 여주시 점동면 가래울길 25-5",
		"REFINE_LOTNO_ADDR": "경기도 여주시 점동면 사곡리 371번지",
		"TELNO": "",
		"REFINE_ZIPNO": "12665",
		"REFINE_WGS84_LAT": "37.2056449942",
		"REFINE_WGS84_LOGT": "127.6752503847",
		"DATA_STD_DE": "2020-08-18"
	},
	{
		"SIGUN_NM": "여주시",
		"CMPNM_NM": "오갑산구이마당",
		"INDUTYPE_NM": "일반휴게음식-일반한식",
		"REFINE_ROADNM_ADDR": "경기도 여주시 점동면 청안리길 4",
		"REFINE_LOTNO_ADDR": "경기도 여주시 점동면 청안리 156-4번지",
		"TELNO": "",
		"REFINE_ZIPNO": "12667",
		"REFINE_WGS84_LAT": "37.2067093996",
		"REFINE_WGS84_LOGT": "127.6620674791",
		"DATA_STD_DE": "2020-08-18"
	},
	{
		"SIGUN_NM": "여주시",
		"CMPNM_NM": "오갑산정육점",
		"INDUTYPE_NM": "음료식품-정육점",
		"REFINE_ROADNM_ADDR": "경기도 여주시 점동면 청안리길 4",
		"REFINE_LOTNO_ADDR": "경기도 여주시 점동면 청안리 156-4번지",
		"TELNO": "",
		"REFINE_ZIPNO": "12667",
		"REFINE_WGS84_LAT": "37.2067093996",
		"REFINE_WGS84_LOGT": "127.6620674791",
		"DATA_STD_DE": "2020-08-18"
	},
	{
		"SIGUN_NM": "여주시",
		"CMPNM_NM": "용진카공업사",
		"INDUTYPE_NM": "자동차정비 유지-자동차정비",
		"REFINE_ROADNM_ADDR": "경기도 여주시 점동면 장여로 1335",
		"REFINE_LOTNO_ADDR": "경기도 여주시 점동면 처리 520-6번지",
		"TELNO": "",
		"REFINE_ZIPNO": "12666",
		"REFINE_WGS84_LAT": "37.2191250853",
		"REFINE_WGS84_LOGT": "127.6662080952",
		"DATA_STD_DE": "2020-08-18"
	},
	{
		"SIGUN_NM": "여주시",
		"CMPNM_NM": "우리집 시골밥상",
		"INDUTYPE_NM": "일반휴게음식-일반한식",
		"REFINE_ROADNM_ADDR": "경기도 여주시 점동면 장여로 1315-5",
		"REFINE_LOTNO_ADDR": "경기도 여주시 점동면 처리 551-5번지",
		"TELNO": "",
		"REFINE_ZIPNO": "12666",
		"REFINE_WGS84_LAT": "37.2169976566",
		"REFINE_WGS84_LOGT": "127.6662823253",
		"DATA_STD_DE": "2020-08-18"
	},
	{
		"SIGUN_NM": "여주시",
		"CMPNM_NM": "우성전자",
		"INDUTYPE_NM": "전기제품-가전제품",
		"REFINE_ROADNM_ADDR": "경기도 여주시 점동면 장여로 589-10",
		"REFINE_LOTNO_ADDR": "경기도 여주시 점동면 원부리 145번지",
		"TELNO": "",
		"REFINE_ZIPNO": "12667",
		"REFINE_WGS84_LAT": "37.1648679681",
		"REFINE_WGS84_LOGT": "127.6390572172",
		"DATA_STD_DE": "2020-08-18"
	},
	{
		"SIGUN_NM": "여주시",
		"CMPNM_NM": "원부제유소",
		"INDUTYPE_NM": "음료식품-기타음료식품",
		"REFINE_ROADNM_ADDR": "경기도 여주시 점동면 장여로 525-16",
		"REFINE_LOTNO_ADDR": "경기도 여주시 점동면 원부리 175번지",
		"TELNO": "",
		"REFINE_ZIPNO": "12667",
		"REFINE_WGS84_LAT": "37.1638672472",
		"REFINE_WGS84_LOGT": "127.6312837860",
		"DATA_STD_DE": "2020-08-18"
	},
	{
		"SIGUN_NM": "여주시",
		"CMPNM_NM": "원진농자재",
		"INDUTYPE_NM": "농업-기타농업관련",
		"REFINE_ROADNM_ADDR": "경기도 여주시 점동면 가남로 1115",
		"REFINE_LOTNO_ADDR": "경기도 여주시 점동면 청안리 317번지",
		"TELNO": "",
		"REFINE_ZIPNO": "12667",
		"REFINE_WGS84_LAT": "37.2032387401",
		"REFINE_WGS84_LOGT": "127.6555127517",
		"DATA_STD_DE": "2020-08-18"
	},
	{
		"SIGUN_NM": "여주시",
		"CMPNM_NM": "원창카센타",
		"INDUTYPE_NM": "자동차정비 유지-자동차정비",
		"REFINE_ROADNM_ADDR": "경기도 여주시 점동면 청안로 1",
		"REFINE_LOTNO_ADDR": "경기도 여주시 점동면 청안리 34번지",
		"TELNO": "",
		"REFINE_ZIPNO": "12667",
		"REFINE_WGS84_LAT": "37.1948737947",
		"REFINE_WGS84_LOGT": "127.6621210515",
		"DATA_STD_DE": "2020-08-18"
	},
	{
		"SIGUN_NM": "여주시",
		"CMPNM_NM": "웰빙은혜농산",
		"INDUTYPE_NM": "음료식품-농•축•수산품",
		"REFINE_ROADNM_ADDR": "경기도 여주시 점동면 가래울길 23",
		"REFINE_LOTNO_ADDR": "경기도 여주시 점동면 사곡리 371번지 23호",
		"TELNO": "",
		"REFINE_ZIPNO": "12665",
		"REFINE_WGS84_LAT": "37.2055101163",
		"REFINE_WGS84_LOGT": "127.6750246855",
		"DATA_STD_DE": "2020-08-18"
	},
	{
		"SIGUN_NM": "여주시",
		"CMPNM_NM": "유닉컨설팅",
		"INDUTYPE_NM": "유통업 영리-기타유통업",
		"REFINE_ROADNM_ADDR": "경기도 여주시 점동면 모래실2길 5-11",
		"REFINE_LOTNO_ADDR": "경기도 여주시 점동면 사곡리 179-3번지",
		"TELNO": "",
		"REFINE_ZIPNO": "12665",
		"REFINE_WGS84_LAT": "37.2021481952",
		"REFINE_WGS84_LOGT": "127.6866125838",
		"DATA_STD_DE": "2020-08-18"
	},
	{
		"SIGUN_NM": "여주시",
		"CMPNM_NM": "이세용도예연구소",
		"INDUTYPE_NM": "문화.취미-민예•공예품",
		"REFINE_ROADNM_ADDR": "경기도 여주시 점동면 처리길 86",
		"REFINE_LOTNO_ADDR": "경기도 여주시 점동면 처리 263번지",
		"TELNO": "",
		"REFINE_ZIPNO": "12666",
		"REFINE_WGS84_LAT": "37.2276153367",
		"REFINE_WGS84_LOGT": "127.6732045002",
		"DATA_STD_DE": "2020-08-18"
	},
	{
		"SIGUN_NM": "여주시",
		"CMPNM_NM": "이화가든",
		"INDUTYPE_NM": "일반휴게음식-일반한식",
		"REFINE_ROADNM_ADDR": "경기도 여주시 점동면 안말2길 62",
		"REFINE_LOTNO_ADDR": "경기도 여주시 점동면 청안리 169-1번지",
		"TELNO": "",
		"REFINE_ZIPNO": "12667",
		"REFINE_WGS84_LAT": "37.2097000905",
		"REFINE_WGS84_LOGT": "127.6635164336",
		"DATA_STD_DE": "2020-08-18"
	},
	{
		"SIGUN_NM": "여주시",
		"CMPNM_NM": "자연농원",
		"INDUTYPE_NM": "문화.취미-화원",
		"REFINE_ROADNM_ADDR": "경기도 여주시 점동면 선사길 177-1",
		"REFINE_LOTNO_ADDR": "경기도 여주시 점동면 흔암리 177-5번지",
		"TELNO": "",
		"REFINE_ZIPNO": "12666",
		"REFINE_WGS84_LAT": "37.2393268308",
		"REFINE_WGS84_LOGT": "127.6716754265",
		"DATA_STD_DE": "2020-08-18"
	},
	{
		"SIGUN_NM": "여주시",
		"CMPNM_NM": "장터골",
		"INDUTYPE_NM": "일반휴게음식-일반한식",
		"REFINE_ROADNM_ADDR": "경기도 여주시 점동면 점동로 124",
		"REFINE_LOTNO_ADDR": "경기도 여주시 점동면 사곡리 356-1번지",
		"TELNO": "",
		"REFINE_ZIPNO": "12665",
		"REFINE_WGS84_LAT": "37.2052345960",
		"REFINE_WGS84_LOGT": "127.6723532194",
		"DATA_STD_DE": "2020-08-18"
	},
	{
		"SIGUN_NM": "여주시",
		"CMPNM_NM": "재형이네",
		"INDUTYPE_NM": "일반휴게음식-일반한식",
		"REFINE_ROADNM_ADDR": "경기도 여주시 점동면 청안리길 5",
		"REFINE_LOTNO_ADDR": "경기도 여주시 점동면 청안리 155-4번지",
		"TELNO": "",
		"REFINE_ZIPNO": "12667",
		"REFINE_WGS84_LAT": "37.2064125202",
		"REFINE_WGS84_LOGT": "127.6616386032",
		"DATA_STD_DE": "2020-08-18"
	},
	{
		"SIGUN_NM": "여주시",
		"CMPNM_NM": "전통현악기연구원",
		"INDUTYPE_NM": "레져용품-악기점",
		"REFINE_ROADNM_ADDR": "경기도 여주시 점동면 삼합리길 79",
		"REFINE_LOTNO_ADDR": "경기도 여주시 점동면 삼합리 411-1번지",
		"TELNO": "",
		"REFINE_ZIPNO": "12665",
		"REFINE_WGS84_LAT": "37.2061305208",
		"REFINE_WGS84_LOGT": "127.7288264840",
		"DATA_STD_DE": "2020-08-18"
	},
	{
		"SIGUN_NM": "여주시",
		"CMPNM_NM": "점동농업협동조합",
		"INDUTYPE_NM": "유통업 비영리-농,축협 직영매장",
		"REFINE_ROADNM_ADDR": "경기도 여주시 점동면 청안리길 8",
		"REFINE_LOTNO_ADDR": "경기도 여주시 점동면 청안리 154-3",
		"TELNO": "",
		"REFINE_ZIPNO": "12667",
		"REFINE_WGS84_LAT": "37.2071337694",
		"REFINE_WGS84_LOGT": "127.6615499846",
		"DATA_STD_DE": "2020-08-18"
	},
	{
		"SIGUN_NM": "여주시",
		"CMPNM_NM": "점동농협하나로마트",
		"INDUTYPE_NM": "유통업 비영리-농,축협 직영매장",
		"REFINE_ROADNM_ADDR": "경기도 여주시 점동면 청안리길 8",
		"REFINE_LOTNO_ADDR": "경기도 여주시 점동면 청안리 154-3번지 농협",
		"TELNO": "",
		"REFINE_ZIPNO": "12667",
		"REFINE_WGS84_LAT": "37.2071337694",
		"REFINE_WGS84_LOGT": "127.6615499846",
		"DATA_STD_DE": "2020-08-18"
	},
	{
		"SIGUN_NM": "여주시",
		"CMPNM_NM": "점동농협하나로마트(농산물)",
		"INDUTYPE_NM": "유통업 비영리-농,축협 직영매장",
		"REFINE_ROADNM_ADDR": "경기도 여주시 점동면 청안리길 8",
		"REFINE_LOTNO_ADDR": "경기도 여주시 점동면 청안리 154-3번지 농협",
		"TELNO": "",
		"REFINE_ZIPNO": "12667",
		"REFINE_WGS84_LAT": "37.2071337694",
		"REFINE_WGS84_LOGT": "127.6615499846",
		"DATA_STD_DE": "2020-08-18"
	},
	{
		"SIGUN_NM": "여주시",
		"CMPNM_NM": "점동떡방앗간",
		"INDUTYPE_NM": "음료식품-제과점",
		"REFINE_ROADNM_ADDR": "경기도 여주시 점동면 청안로 119",
		"REFINE_LOTNO_ADDR": "경기도 여주시 점동면 청안리 127-7번지",
		"TELNO": "",
		"REFINE_ZIPNO": "12667",
		"REFINE_WGS84_LAT": "37.2052950048",
		"REFINE_WGS84_LOGT": "127.6614671799",
		"DATA_STD_DE": "2020-08-18"
	},
	{
		"SIGUN_NM": "여주시",
		"CMPNM_NM": "점동면주민자취위원회",
		"INDUTYPE_NM": "음료식품-농•축•수산품",
		"REFINE_ROADNM_ADDR": "경기도 여주시 점동면 청안로 130-3",
		"REFINE_LOTNO_ADDR": "경기도 여주시 점동면 청안리 124-6번지",
		"TELNO": "",
		"REFINE_ZIPNO": "12667",
		"REFINE_WGS84_LAT": "37.2058337506",
		"REFINE_WGS84_LOGT": "127.6630009681",
		"DATA_STD_DE": "2020-08-18"
	},
	{
		"SIGUN_NM": "여주시",
		"CMPNM_NM": "점동숯불갈비",
		"INDUTYPE_NM": "일반휴게음식-일반한식",
		"REFINE_ROADNM_ADDR": "경기도 여주시 점동면 안말2길 14-10",
		"REFINE_LOTNO_ADDR": "경기도 여주시 점동면 청안리 147-1번지",
		"TELNO": "",
		"REFINE_ZIPNO": "12667",
		"REFINE_WGS84_LAT": "37.2066213611",
		"REFINE_WGS84_LOGT": "127.6605233649",
		"DATA_STD_DE": "2020-08-18"
	},
	{
		"SIGUN_NM": "여주시",
		"CMPNM_NM": "점동연세의원",
		"INDUTYPE_NM": "의원-의원",
		"REFINE_ROADNM_ADDR": "경기도 여주시 점동면 청안로 121",
		"REFINE_LOTNO_ADDR": "경기도 여주시 점동면 청안리 127-5번지",
		"TELNO": "",
		"REFINE_ZIPNO": "12667",
		"REFINE_WGS84_LAT": "37.2054661494",
		"REFINE_WGS84_LOGT": "127.6615576994",
		"DATA_STD_DE": "2020-08-18"
	},
	{
		"SIGUN_NM": "여주시",
		"CMPNM_NM": "점동오토바이",
		"INDUTYPE_NM": "수리서비스-레져용품수리",
		"REFINE_ROADNM_ADDR": "경기도 여주시 점동면 청안로 130-8",
		"REFINE_LOTNO_ADDR": "경기도 여주시 점동면 청안리 130-9번지",
		"TELNO": "",
		"REFINE_ZIPNO": "12667",
		"REFINE_WGS84_LAT": "37.2056361066",
		"REFINE_WGS84_LOGT": "127.6625159594",
		"DATA_STD_DE": "2020-08-18"
	},
	{
		"SIGUN_NM": "여주시",
		"CMPNM_NM": "점동자율식당",
		"INDUTYPE_NM": "일반휴게음식-일반한식",
		"REFINE_ROADNM_ADDR": "경기도 여주시 점동면 청안로 133",
		"REFINE_LOTNO_ADDR": "경기도 여주시 점동면 청안리 126-2번지",
		"TELNO": "",
		"REFINE_ZIPNO": "12667",
		"REFINE_WGS84_LAT": "37.2064028593",
		"REFINE_WGS84_LOGT": "127.6621119016",
		"DATA_STD_DE": "2020-08-18"
	},
	{
		"SIGUN_NM": "여주시",
		"CMPNM_NM": "점동전기",
		"INDUTYPE_NM": "전기제품-가전제품",
		"REFINE_ROADNM_ADDR": "경기도 여주시 점동면 청안리길 5",
		"REFINE_LOTNO_ADDR": "경기도 여주시 점동면 청안리 155-4번지",
		"TELNO": "",
		"REFINE_ZIPNO": "12667",
		"REFINE_WGS84_LAT": "37.2064125202",
		"REFINE_WGS84_LOGT": "127.6616386032",
		"DATA_STD_DE": "2020-08-18"
	},
	{
		"SIGUN_NM": "여주시",
		"CMPNM_NM": "점동정육점",
		"INDUTYPE_NM": "음료식품-정육점",
		"REFINE_ROADNM_ADDR": "경기도 여주시 점동면 청안리길 4",
		"REFINE_LOTNO_ADDR": "경기도 여주시 점동면 청안리 156-4번지",
		"TELNO": "",
		"REFINE_ZIPNO": "12667",
		"REFINE_WGS84_LAT": "37.2067093996",
		"REFINE_WGS84_LOGT": "127.6620674791",
		"DATA_STD_DE": "2020-08-18"
	},
	{
		"SIGUN_NM": "여주시",
		"CMPNM_NM": "점동정육점식당",
		"INDUTYPE_NM": "일반휴게음식-일반한식",
		"REFINE_ROADNM_ADDR": "경기도 여주시 점동면 청안리길 4",
		"REFINE_LOTNO_ADDR": "경기도 여주시 점동면 청안리 156-4번지",
		"TELNO": "",
		"REFINE_ZIPNO": "12667",
		"REFINE_WGS84_LAT": "37.2067093996",
		"REFINE_WGS84_LOGT": "127.6620674791",
		"DATA_STD_DE": "2020-08-18"
	},
	{
		"SIGUN_NM": "여주시",
		"CMPNM_NM": "점동종합마트",
		"INDUTYPE_NM": "음료식품-기타음료식품",
		"REFINE_ROADNM_ADDR": "경기도 여주시 점동면 청안로 130-2",
		"REFINE_LOTNO_ADDR": "경기도 여주시 점동면 청안리 130-3번지",
		"TELNO": "",
		"REFINE_ZIPNO": "12667",
		"REFINE_WGS84_LAT": "37.2059070387",
		"REFINE_WGS84_LOGT": "127.6621446493",
		"DATA_STD_DE": "2020-08-18"
	},
	{
		"SIGUN_NM": "여주시",
		"CMPNM_NM": "점동지물",
		"INDUTYPE_NM": "직물-카페트,커튼,천막,지물",
		"REFINE_ROADNM_ADDR": "경기도 여주시 점동면 청안리길 9",
		"REFINE_LOTNO_ADDR": "경기도 여주시 점동면 청안리 145-3번지",
		"TELNO": "",
		"REFINE_ZIPNO": "12667",
		"REFINE_WGS84_LAT": "37.2065572983",
		"REFINE_WGS84_LOGT": "127.6612332091",
		"DATA_STD_DE": "2020-08-18"
	},
	{
		"SIGUN_NM": "여주시",
		"CMPNM_NM": "점동태권도체육관",
		"INDUTYPE_NM": "학원-예•체능계학원 ",
		"REFINE_ROADNM_ADDR": "경기도 여주시 점동면 청안로 130-2",
		"REFINE_LOTNO_ADDR": "경기도 여주시 점동면 청안리 130-3번지",
		"TELNO": "",
		"REFINE_ZIPNO": "12667",
		"REFINE_WGS84_LAT": "37.2059070387",
		"REFINE_WGS84_LOGT": "127.6621446493",
		"DATA_STD_DE": "2020-08-18"
	},
	{
		"SIGUN_NM": "여주시",
		"CMPNM_NM": "정동종합가스",
		"INDUTYPE_NM": "연료판매점-LPG 취급점",
		"REFINE_ROADNM_ADDR": "경기도 여주시 점동면 모래실1길 23",
		"REFINE_LOTNO_ADDR": "경기도 여주시 점동면 사곡리 174-5번지",
		"TELNO": "",
		"REFINE_ZIPNO": "12665",
		"REFINE_WGS84_LAT": "37.2008726357",
		"REFINE_WGS84_LOGT": "127.6837697378",
		"DATA_STD_DE": "2020-08-18"
	},
	{
		"SIGUN_NM": "여주시",
		"CMPNM_NM": "정의상실",
		"INDUTYPE_NM": "회원제형태-기타4",
		"REFINE_ROADNM_ADDR": "경기도 여주시 점동면 장여로 1413",
		"REFINE_LOTNO_ADDR": "경기도 여주시 점동면 처리 681-4번지",
		"TELNO": "",
		"REFINE_ZIPNO": "12666",
		"REFINE_WGS84_LAT": "37.2255030901",
		"REFINE_WGS84_LOGT": "127.6625698526",
		"DATA_STD_DE": "2020-08-18"
	},
	{
		"SIGUN_NM": "여주시",
		"CMPNM_NM": "제이스베이커리",
		"INDUTYPE_NM": "음료식품-제과점",
		"REFINE_ROADNM_ADDR": "경기도 여주시 점동면 청안리길 5",
		"REFINE_LOTNO_ADDR": "경기도 여주시 점동면 청안리 155-4번지",
		"TELNO": "",
		"REFINE_ZIPNO": "12667",
		"REFINE_WGS84_LAT": "37.2064125202",
		"REFINE_WGS84_LOGT": "127.6616386032",
		"DATA_STD_DE": "2020-08-18"
	},
	{
		"SIGUN_NM": "여주시",
		"CMPNM_NM": "조은상사(포세이돈)",
		"INDUTYPE_NM": "주방용구-주방용구",
		"REFINE_ROADNM_ADDR": "경기도 여주시 점동면 장여로 825",
		"REFINE_LOTNO_ADDR": "경기도 여주시 점동면 덕평리 283-1번지",
		"TELNO": "",
		"REFINE_ZIPNO": "12667",
		"REFINE_WGS84_LAT": "37.1753322309",
		"REFINE_WGS84_LOGT": "127.6613245406",
		"DATA_STD_DE": "2020-08-18"
	},
	{
		"SIGUN_NM": "여주시",
		"CMPNM_NM": "조이당구장",
		"INDUTYPE_NM": "레저업소-당 구 장",
		"REFINE_ROADNM_ADDR": "경기도 여주시 점동면 청안로 147",
		"REFINE_LOTNO_ADDR": "경기도 여주시 점동면 청안리 159-9번지 2층",
		"TELNO": "",
		"REFINE_ZIPNO": "12667",
		"REFINE_WGS84_LAT": "37.2074922324",
		"REFINE_WGS84_LOGT": "127.6630834227",
		"DATA_STD_DE": "2020-08-18"
	},
	{
		"SIGUN_NM": "여주시",
		"CMPNM_NM": "주식회사 수인",
		"INDUTYPE_NM": "농업-비료,사료,종자",
		"REFINE_ROADNM_ADDR": "",
		"REFINE_LOTNO_ADDR": "경기도 여주시 점동면 사곡리 산3-3",
		"TELNO": "",
		"REFINE_ZIPNO": "12665",
		"REFINE_WGS84_LAT": "37.2002313073",
		"REFINE_WGS84_LOGT": "127.6978842853",
		"DATA_STD_DE": "2020-08-18"
	},
	{
		"SIGUN_NM": "여주시",
		"CMPNM_NM": "주식회사 여주허브랜드",
		"INDUTYPE_NM": "숙박업-여관/기타숙박업",
		"REFINE_ROADNM_ADDR": "경기도 여주시 점동면 선사길 377",
		"REFINE_LOTNO_ADDR": "경기도 여주시 점동면 흔암리 66-5번지",
		"TELNO": "",
		"REFINE_ZIPNO": "12666",
		"REFINE_WGS84_LAT": "37.2326649551",
		"REFINE_WGS84_LOGT": "127.6840046990",
		"DATA_STD_DE": "2020-08-18"
	},
	{
		"SIGUN_NM": "여주시",
		"CMPNM_NM": "주식회사 현로보캅스틸",
		"INDUTYPE_NM": "용역 서비스-기타용역서비스",
		"REFINE_ROADNM_ADDR": "경기도 여주시 점동면 청안로 63-10",
		"REFINE_LOTNO_ADDR": "경기도 여주시 점동면 청안리 46번지",
		"TELNO": "",
		"REFINE_ZIPNO": "12667",
		"REFINE_WGS84_LAT": "37.1994557887",
		"REFINE_WGS84_LOGT": "127.6600461835",
		"DATA_STD_DE": "2020-08-18"
	},
	{
		"SIGUN_NM": "여주시",
		"CMPNM_NM": "주식회사아워홈여주소피아그린CC점",
		"INDUTYPE_NM": "일반휴게음식-위탁급식업",
		"REFINE_ROADNM_ADDR": "경기도 여주시 점동면 소피아그린길 84",
		"REFINE_LOTNO_ADDR": "경기도 여주시 점동면 현수리 산13번지 1층",
		"TELNO": "",
		"REFINE_ZIPNO": "12668",
		"REFINE_WGS84_LAT": "37.1717643204",
		"REFINE_WGS84_LOGT": "127.7014405714",
		"DATA_STD_DE": "2020-08-18"
	},
	{
		"SIGUN_NM": "여주시",
		"CMPNM_NM": "주이다원",
		"INDUTYPE_NM": "건강식품-기타건강식품",
		"REFINE_ROADNM_ADDR": "경기도 여주시 점동면 선사길 17-46",
		"REFINE_LOTNO_ADDR": "경기도 여주시 점동면 처리 217-3번지 1층",
		"TELNO": "",
		"REFINE_ZIPNO": "12666",
		"REFINE_WGS84_LAT": "37.2292924903",
		"REFINE_WGS84_LOGT": "127.6665460499",
		"DATA_STD_DE": "2020-08-18"
	},
	{
		"SIGUN_NM": "여주시",
		"CMPNM_NM": "중화요리홍도",
		"INDUTYPE_NM": "일반휴게음식-중국식",
		"REFINE_ROADNM_ADDR": "경기도 여주시 점동면 장여로 885",
		"REFINE_LOTNO_ADDR": "경기도 여주시 점동면 덕평리 169-4번지",
		"TELNO": "",
		"REFINE_ZIPNO": "12667",
		"REFINE_WGS84_LAT": "37.1797827709",
		"REFINE_WGS84_LOGT": "127.6631139603",
		"DATA_STD_DE": "2020-08-18"
	},
	{
		"SIGUN_NM": "여주시",
		"CMPNM_NM": "차차식품",
		"INDUTYPE_NM": "음료식품-기타음료식품",
		"REFINE_ROADNM_ADDR": "경기도 여주시 점동면 청안로 153",
		"REFINE_LOTNO_ADDR": "경기도 여주시 점동면 청안리 161-4번지",
		"TELNO": "",
		"REFINE_ZIPNO": "12667",
		"REFINE_WGS84_LAT": "37.2079153814",
		"REFINE_WGS84_LOGT": "127.6634562342",
		"DATA_STD_DE": "2020-08-18"
	},
	{
		"SIGUN_NM": "여주시",
		"CMPNM_NM": "참새둥지",
		"INDUTYPE_NM": "일반휴게음식-일반한식",
		"REFINE_ROADNM_ADDR": "경기도 여주시 점동면 성주로 634-20",
		"REFINE_LOTNO_ADDR": "경기도 여주시 점동면 성신리 242번지",
		"TELNO": "",
		"REFINE_ZIPNO": "12668",
		"REFINE_WGS84_LAT": "37.1634748387",
		"REFINE_WGS84_LOGT": "127.6640700653",
		"DATA_STD_DE": "2020-08-18"
	},
	{
		"SIGUN_NM": "여주시",
		"CMPNM_NM": "참숯가마찜질방",
		"INDUTYPE_NM": "보건위생-사우나",
		"REFINE_ROADNM_ADDR": "경기도 여주시 점동면 장여로 1049-28",
		"REFINE_LOTNO_ADDR": "경기도 여주시 점동면 청안리 37번지",
		"TELNO": "",
		"REFINE_ZIPNO": "12667",
		"REFINE_WGS84_LAT": "37.1962355237",
		"REFINE_WGS84_LOGT": "127.6616845117",
		"DATA_STD_DE": "2020-08-18"
	},
	{
		"SIGUN_NM": "여주시",
		"CMPNM_NM": "철사랑공업사",
		"INDUTYPE_NM": "수리서비스-기타수리서비스",
		"REFINE_ROADNM_ADDR": "경기도 여주시 점동면 청안로 95",
		"REFINE_LOTNO_ADDR": "경기도 여주시 점동면 청안리 103-2번지",
		"TELNO": "",
		"REFINE_ZIPNO": "12667",
		"REFINE_WGS84_LAT": "37.2031412678",
		"REFINE_WGS84_LOGT": "127.6610005622",
		"DATA_STD_DE": "2020-08-18"
	},
	{
		"SIGUN_NM": "여주시",
		"CMPNM_NM": "청안가스",
		"INDUTYPE_NM": "연료판매점-LPG 취급점",
		"REFINE_ROADNM_ADDR": "경기도 여주시 점동면 청안로 130-2",
		"REFINE_LOTNO_ADDR": "경기도 여주시 점동면 청안리 130-3번지",
		"TELNO": "",
		"REFINE_ZIPNO": "12667",
		"REFINE_WGS84_LAT": "37.2059070387",
		"REFINE_WGS84_LOGT": "127.6621446493",
		"DATA_STD_DE": "2020-08-18"
	},
	{
		"SIGUN_NM": "여주시",
		"CMPNM_NM": "청안이발관",
		"INDUTYPE_NM": "보건위생-이용원",
		"REFINE_ROADNM_ADDR": "경기도 여주시 점동면 청안리길 9",
		"REFINE_LOTNO_ADDR": "경기도 여주시 점동면 청안리 145-3번지 1층 108호",
		"TELNO": "",
		"REFINE_ZIPNO": "12667",
		"REFINE_WGS84_LAT": "37.2065572983",
		"REFINE_WGS84_LOGT": "127.6612332091",
		"DATA_STD_DE": "2020-08-18"
	},
	{
		"SIGUN_NM": "여주시",
		"CMPNM_NM": "청안철물",
		"INDUTYPE_NM": "기타-기계공구",
		"REFINE_ROADNM_ADDR": "경기도 여주시 점동면 청안로 130-2",
		"REFINE_LOTNO_ADDR": "경기도 여주시 점동면 청안리 130-3번지",
		"TELNO": "",
		"REFINE_ZIPNO": "12667",
		"REFINE_WGS84_LAT": "37.2059070387",
		"REFINE_WGS84_LOGT": "127.6621446493",
		"DATA_STD_DE": "2020-08-18"
	},
	{
		"SIGUN_NM": "여주시",
		"CMPNM_NM": "충전종합설비",
		"INDUTYPE_NM": "건축자재-보일러•펌프•샷시",
		"REFINE_ROADNM_ADDR": "경기도 여주시 점동면 청안로 120",
		"REFINE_LOTNO_ADDR": "경기도 여주시 점동면 청안리 128-8번지",
		"TELNO": "",
		"REFINE_ZIPNO": "12667",
		"REFINE_WGS84_LAT": "37.2052225539",
		"REFINE_WGS84_LOGT": "127.6617149506",
		"DATA_STD_DE": "2020-08-18"
	},
	{
		"SIGUN_NM": "여주시",
		"CMPNM_NM": "커피나라",
		"INDUTYPE_NM": "음료식품-기타음료식품",
		"REFINE_ROADNM_ADDR": "경기도 여주시 점동면 점동로 342",
		"REFINE_LOTNO_ADDR": "경기도 여주시 점동면 사곡리 86-3",
		"TELNO": "",
		"REFINE_ZIPNO": "12665",
		"REFINE_WGS84_LAT": "37.2007375292",
		"REFINE_WGS84_LOGT": "127.6949817200",
		"DATA_STD_DE": "2020-08-18"
	},
	{
		"SIGUN_NM": "여주시",
		"CMPNM_NM": "커피나라",
		"INDUTYPE_NM": "음료식품-기타음료식품",
		"REFINE_ROADNM_ADDR": "경기도 여주시 점동면 점동로 342",
		"REFINE_LOTNO_ADDR": "경기도 여주시 점동면 사곡리 86-3",
		"TELNO": "",
		"REFINE_ZIPNO": "12665",
		"REFINE_WGS84_LAT": "37.2007375292",
		"REFINE_WGS84_LOGT": "127.6949817200",
		"DATA_STD_DE": "2020-08-18"
	},
	{
		"SIGUN_NM": "여주시",
		"CMPNM_NM": "케이제이(KJ)주유소",
		"INDUTYPE_NM": "연료판매점-현대정유(오일뱅크)",
		"REFINE_ROADNM_ADDR": "경기도 여주시 점동면 청안로 180",
		"REFINE_LOTNO_ADDR": "경기도 여주시 점동면 청안리 166-13번지",
		"TELNO": "",
		"REFINE_ZIPNO": "12667",
		"REFINE_WGS84_LAT": "37.2102303910",
		"REFINE_WGS84_LOGT": "127.6646220446",
		"DATA_STD_DE": "2020-08-18"
	},
	{
		"SIGUN_NM": "여주시",
		"CMPNM_NM": "크린카",
		"INDUTYPE_NM": "자동차정비 유지-세차장",
		"REFINE_ROADNM_ADDR": "경기도 여주시 점동면 안말2길 27-19",
		"REFINE_LOTNO_ADDR": "경기도 여주시 점동면 청안리 150-26번지",
		"TELNO": "",
		"REFINE_ZIPNO": "12667",
		"REFINE_WGS84_LAT": "37.2086329009",
		"REFINE_WGS84_LOGT": "127.6594908011",
		"DATA_STD_DE": "2020-08-18"
	},
	{
		"SIGUN_NM": "여주시",
		"CMPNM_NM": "태산산업",
		"INDUTYPE_NM": "농업-비료,사료,종자",
		"REFINE_ROADNM_ADDR": "경기도 여주시 점동면 청안로 139",
		"REFINE_LOTNO_ADDR": "경기도 여주시 점동면 청안리 154-4번지",
		"TELNO": "",
		"REFINE_ZIPNO": "12667",
		"REFINE_WGS84_LAT": "37.2068804357",
		"REFINE_WGS84_LOGT": "127.6622368884",
		"DATA_STD_DE": "2020-08-18"
	},
	{
		"SIGUN_NM": "여주시",
		"CMPNM_NM": "테라산타",
		"INDUTYPE_NM": "일반휴게음식-서양음식",
		"REFINE_ROADNM_ADDR": "경기도 여주시 점동면 선사길 295",
		"REFINE_LOTNO_ADDR": "경기도 여주시 점동면 흔암리 111-5번지",
		"TELNO": "",
		"REFINE_ZIPNO": "12666",
		"REFINE_WGS84_LAT": "37.2390045337",
		"REFINE_WGS84_LOGT": "127.6822613094",
		"DATA_STD_DE": "2020-08-18"
	},
	{
		"SIGUN_NM": "여주시",
		"CMPNM_NM": "토담집",
		"INDUTYPE_NM": "일반휴게음식-일반한식",
		"REFINE_ROADNM_ADDR": "경기도 여주시 점동면 수롱길 56",
		"REFINE_LOTNO_ADDR": "경기도 여주시 점동면 현수리 114번지",
		"TELNO": "",
		"REFINE_ZIPNO": "12668",
		"REFINE_WGS84_LAT": "37.1928869530",
		"REFINE_WGS84_LOGT": "127.6945446341",
		"DATA_STD_DE": "2020-08-18"
	},
	{
		"SIGUN_NM": "여주시",
		"CMPNM_NM": "토리샘",
		"INDUTYPE_NM": "숙박업-여관/기타숙박업",
		"REFINE_ROADNM_ADDR": "경기도 여주시 점동면 어우실길 67",
		"REFINE_LOTNO_ADDR": "경기도 여주시 점동면 관한리 419번지",
		"TELNO": "",
		"REFINE_ZIPNO": "12668",
		"REFINE_WGS84_LAT": "37.1520523725",
		"REFINE_WGS84_LOGT": "127.6585498059",
		"DATA_STD_DE": "2020-08-18"
	},
	{
		"SIGUN_NM": "여주시",
		"CMPNM_NM": "토리샘",
		"INDUTYPE_NM": "음료식품-기타음료식품",
		"REFINE_ROADNM_ADDR": "경기도 여주시 점동면 어우실길 67",
		"REFINE_LOTNO_ADDR": "경기도 여주시 점동면 관한리 419번지",
		"TELNO": "",
		"REFINE_ZIPNO": "12668",
		"REFINE_WGS84_LAT": "37.1520523725",
		"REFINE_WGS84_LOGT": "127.6585498059",
		"DATA_STD_DE": "2020-08-18"
	},
	{
		"SIGUN_NM": "여주시",
		"CMPNM_NM": "토리샘",
		"INDUTYPE_NM": "일반휴게음식-일반한식",
		"REFINE_ROADNM_ADDR": "경기도 여주시 점동면 어우실길 67",
		"REFINE_LOTNO_ADDR": "경기도 여주시 점동면 관한리 419번지",
		"TELNO": "",
		"REFINE_ZIPNO": "12668",
		"REFINE_WGS84_LAT": "37.1520523725",
		"REFINE_WGS84_LOGT": "127.6585498059",
		"DATA_STD_DE": "2020-08-18"
	},
	{
		"SIGUN_NM": "여주시",
		"CMPNM_NM": "폰M텔레콤",
		"INDUTYPE_NM": "사무통신-통신기기",
		"REFINE_ROADNM_ADDR": "",
		"REFINE_LOTNO_ADDR": "경기도 여주시 점동면 당진리 7-1",
		"TELNO": "",
		"REFINE_ZIPNO": "12668",
		"REFINE_WGS84_LAT": "37.1649257508",
		"REFINE_WGS84_LOGT": "127.6923031892",
		"DATA_STD_DE": "2020-08-18"
	},
	{
		"SIGUN_NM": "여주시",
		"CMPNM_NM": "풍년방앗간",
		"INDUTYPE_NM": "음료식품-제과점",
		"REFINE_ROADNM_ADDR": "경기도 여주시 점동면 청안로 133",
		"REFINE_LOTNO_ADDR": "경기도 여주시 점동면 청안리 126-2번지",
		"TELNO": "",
		"REFINE_ZIPNO": "12667",
		"REFINE_WGS84_LAT": "37.2064028593",
		"REFINE_WGS84_LOGT": "127.6621119016",
		"DATA_STD_DE": "2020-08-18"
	},
	{
		"SIGUN_NM": "여주시",
		"CMPNM_NM": "하나미용실",
		"INDUTYPE_NM": "보건위생-미용원",
		"REFINE_ROADNM_ADDR": "경기도 여주시 점동면 청안로 125",
		"REFINE_LOTNO_ADDR": "경기도 여주시 점동면 청안리 127-2번지",
		"TELNO": "",
		"REFINE_ZIPNO": "12667",
		"REFINE_WGS84_LAT": "37.2057815500",
		"REFINE_WGS84_LOGT": "127.6616259881",
		"DATA_STD_DE": "2020-08-18"
	},
	{
		"SIGUN_NM": "여주시",
		"CMPNM_NM": "한신공업사",
		"INDUTYPE_NM": "자동차정비 유지-중장비수리",
		"REFINE_ROADNM_ADDR": "경기도 여주시 점동면 수롱길 43-12",
		"REFINE_LOTNO_ADDR": "경기도 여주시 점동면 현수리 282번지",
		"TELNO": "",
		"REFINE_ZIPNO": "12668",
		"REFINE_WGS84_LAT": "37.1927996671",
		"REFINE_WGS84_LOGT": "127.6927979519",
		"DATA_STD_DE": "2020-08-18"
	},
	{
		"SIGUN_NM": "여주시",
		"CMPNM_NM": "한양왕소금구이",
		"INDUTYPE_NM": "일반휴게음식-일반한식",
		"REFINE_ROADNM_ADDR": "",
		"REFINE_LOTNO_ADDR": "경기도 여주시 점동면 청안리 159번지 청안빌라",
		"TELNO": "",
		"REFINE_ZIPNO": "12667",
		"REFINE_WGS84_LAT": "37.2076644752",
		"REFINE_WGS84_LOGT": "127.6623738030",
		"DATA_STD_DE": "2020-08-18"
	},
	{
		"SIGUN_NM": "여주시",
		"CMPNM_NM": "한양정육점",
		"INDUTYPE_NM": "음료식품-정육점",
		"REFINE_ROADNM_ADDR": "경기도 여주시 점동면 청안로 143",
		"REFINE_LOTNO_ADDR": "경기도 여주시 점동면 청안리 159-6번지",
		"TELNO": "",
		"REFINE_ZIPNO": "12667",
		"REFINE_WGS84_LAT": "37.2072492244",
		"REFINE_WGS84_LOGT": "127.6628124288",
		"DATA_STD_DE": "2020-08-18"
	},
	{
		"SIGUN_NM": "여주시",
		"CMPNM_NM": "한우만세",
		"INDUTYPE_NM": "음료식품-정육점",
		"REFINE_ROADNM_ADDR": "경기도 여주시 점동면 점동로 205",
		"REFINE_LOTNO_ADDR": "경기도 여주시 점동면 사곡리 286-11번지",
		"TELNO": "",
		"REFINE_ZIPNO": "12665",
		"REFINE_WGS84_LAT": "37.2038871396",
		"REFINE_WGS84_LOGT": "127.6813091085",
		"DATA_STD_DE": "2020-08-18"
	},
	{
		"SIGUN_NM": "여주시",
		"CMPNM_NM": "한우만세",
		"INDUTYPE_NM": "일반휴게음식-일반한식",
		"REFINE_ROADNM_ADDR": "경기도 여주시 점동면 점동로 205",
		"REFINE_LOTNO_ADDR": "경기도 여주시 점동면 사곡리 286-11번지",
		"TELNO": "",
		"REFINE_ZIPNO": "12665",
		"REFINE_WGS84_LAT": "37.2038871396",
		"REFINE_WGS84_LOGT": "127.6813091085",
		"DATA_STD_DE": "2020-08-18"
	},
	{
		"SIGUN_NM": "여주시",
		"CMPNM_NM": "한추어탕",
		"INDUTYPE_NM": "일반휴게음식-일반한식",
		"REFINE_ROADNM_ADDR": "경기도 여주시 점동면 장여로 680-6",
		"REFINE_LOTNO_ADDR": "경기도 여주시 점동면 덕평리 557-8번지",
		"TELNO": "",
		"REFINE_ZIPNO": "12667",
		"REFINE_WGS84_LAT": "37.1667135158",
		"REFINE_WGS84_LOGT": "127.6484319190",
		"DATA_STD_DE": "2020-08-18"
	},
	{
		"SIGUN_NM": "여주시",
		"CMPNM_NM": "해물칼국수",
		"INDUTYPE_NM": "일반휴게음식-일반한식",
		"REFINE_ROADNM_ADDR": "경기도 여주시 점동면 청안리길 9",
		"REFINE_LOTNO_ADDR": "경기도 여주시 점동면 청안리 145-3번지",
		"TELNO": "",
		"REFINE_ZIPNO": "12667",
		"REFINE_WGS84_LAT": "37.2065572983",
		"REFINE_WGS84_LOGT": "127.6612332091",
		"DATA_STD_DE": "2020-08-18"
	},
	{
		"SIGUN_NM": "여주시",
		"CMPNM_NM": "헤어컬렉션",
		"INDUTYPE_NM": "보건위생-미용원",
		"REFINE_ROADNM_ADDR": "경기도 여주시 점동면 청안로 139",
		"REFINE_LOTNO_ADDR": "경기도 여주시 점동면 청안리 154-4번지",
		"TELNO": "",
		"REFINE_ZIPNO": "12667",
		"REFINE_WGS84_LAT": "37.2068804357",
		"REFINE_WGS84_LOGT": "127.6622368884",
		"DATA_STD_DE": "2020-08-18"
	},
	{
		"SIGUN_NM": "여주시",
		"CMPNM_NM": "현대PC식당",
		"INDUTYPE_NM": "일반휴게음식-일반한식",
		"REFINE_ROADNM_ADDR": "경기도 여주시 점동면 장여로 849",
		"REFINE_LOTNO_ADDR": "경기도 여주시 점동면 덕평리 188-5번지",
		"TELNO": "",
		"REFINE_ZIPNO": "12667",
		"REFINE_WGS84_LAT": "37.1809304300",
		"REFINE_WGS84_LOGT": "127.6610210051",
		"DATA_STD_DE": "2020-08-18"
	},
	{
		"SIGUN_NM": "여주시",
		"CMPNM_NM": "현미용실",
		"INDUTYPE_NM": "보건위생-미용원",
		"REFINE_ROADNM_ADDR": "경기도 여주시 점동면 청안로 133",
		"REFINE_LOTNO_ADDR": "경기도 여주시 점동면 청안리 126-2번지",
		"TELNO": "",
		"REFINE_ZIPNO": "12667",
		"REFINE_WGS84_LAT": "37.2064028593",
		"REFINE_WGS84_LOGT": "127.6621119016",
		"DATA_STD_DE": "2020-08-18"
	},
	{
		"SIGUN_NM": "여주시",
		"CMPNM_NM": "현성선업",
		"INDUTYPE_NM": "건축자재-기타건축자재",
		"REFINE_ROADNM_ADDR": "경기도 여주시 점동면 청안로 212",
		"REFINE_LOTNO_ADDR": "경기도 여주시 점동면 처리 543-3번지",
		"TELNO": "",
		"REFINE_ZIPNO": "12666",
		"REFINE_WGS84_LAT": "37.2127526958",
		"REFINE_WGS84_LOGT": "127.6657996506",
		"DATA_STD_DE": "2020-08-18"
	},
	{
		"SIGUN_NM": "여주시",
		"CMPNM_NM": "호정슈퍼",
		"INDUTYPE_NM": "유통업 영리-슈퍼마켓",
		"REFINE_ROADNM_ADDR": "경기도 여주시 점동면 선사길 353",
		"REFINE_LOTNO_ADDR": "경기도 여주시 점동면 흔암리 46-8번지",
		"TELNO": "",
		"REFINE_ZIPNO": "12666",
		"REFINE_WGS84_LAT": "37.2352341978",
		"REFINE_WGS84_LOGT": "127.6838531101",
		"DATA_STD_DE": "2020-08-18"
	},
	{
		"SIGUN_NM": "여주시",
		"CMPNM_NM": "화림가든",
		"INDUTYPE_NM": "음료식품-미곡상",
		"REFINE_ROADNM_ADDR": "경기도 여주시 점동면 청안로 178",
		"REFINE_LOTNO_ADDR": "경기도 여주시 점동면 청안리 166-11번지",
		"TELNO": "",
		"REFINE_ZIPNO": "12667",
		"REFINE_WGS84_LAT": "37.2098157750",
		"REFINE_WGS84_LOGT": "127.6645986039",
		"DATA_STD_DE": "2020-08-18"
	},
	{
		"SIGUN_NM": "여주시",
		"CMPNM_NM": "화림가든",
		"INDUTYPE_NM": "일반휴게음식-일반한식",
		"REFINE_ROADNM_ADDR": "경기도 여주시 점동면 청안로 178",
		"REFINE_LOTNO_ADDR": "경기도 여주시 점동면 청안리 166-11번지",
		"TELNO": "",
		"REFINE_ZIPNO": "12667",
		"REFINE_WGS84_LAT": "37.2098157750",
		"REFINE_WGS84_LOGT": "127.6645986039",
		"DATA_STD_DE": "2020-08-18"
	},
	{
		"SIGUN_NM": "여주시",
		"CMPNM_NM": "황토가든",
		"INDUTYPE_NM": "일반휴게음식-일반한식",
		"REFINE_ROADNM_ADDR": "경기도 여주시 점동면 청안로 172",
		"REFINE_LOTNO_ADDR": "경기도 여주시 점동면 청안리 166-19번지",
		"TELNO": "",
		"REFINE_ZIPNO": "12667",
		"REFINE_WGS84_LAT": "37.2095724107",
		"REFINE_WGS84_LOGT": "127.6645868054",
		"DATA_STD_DE": "2020-08-18"
	},
	{
		"SIGUN_NM": "여주시",
		"CMPNM_NM": "희망오토바이",
		"INDUTYPE_NM": "자동차판매-이륜차판매",
		"REFINE_ROADNM_ADDR": "경기도 여주시 점동면 청안로 119-1",
		"REFINE_LOTNO_ADDR": "경기도 여주시 점동면 청안리 127-7번지",
		"TELNO": "",
		"REFINE_ZIPNO": "12667",
		"REFINE_WGS84_LAT": "37.2053580572",
		"REFINE_WGS84_LOGT": "127.6615011222",
		"DATA_STD_DE": "2020-08-18"
	}
]