[
	{
		"SIGUN_NM": "고양시",
		"CMPNM_NM": "갯마을세꼬시",
		"INDUTYPE_NM": "일반휴게음식-일반한식",
		"REFINE_ROADNM_ADDR": "경기도 고양시 일산서구 중앙로 1493",
		"REFINE_LOTNO_ADDR": "경기도 고양시 일산서구 주엽2동 138번지 문촌마을제상가동제 1층 1001-10호",
		"TELNO": "",
		"REFINE_ZIPNO": "10379",
		"REFINE_WGS84_LAT": "37.6724871385",
		"REFINE_WGS84_LOGT": "126.7547653726",
		"DATA_STD_DE": "2020-08-18"
	},
	{
		"SIGUN_NM": "고양시",
		"CMPNM_NM": "그랜드당구장",
		"INDUTYPE_NM": "레저업소-당 구 장",
		"REFINE_ROADNM_ADDR": "경기도 고양시 일산서구 강성로 147",
		"REFINE_LOTNO_ADDR": "경기도 고양시 일산서구 주엽2동 18-1번지 동문시티프라자 5층",
		"TELNO": "",
		"REFINE_ZIPNO": "10387",
		"REFINE_WGS84_LAT": "37.6717770287",
		"REFINE_WGS84_LOGT": "126.7593648793",
		"DATA_STD_DE": "2020-08-18"
	},
	{
		"SIGUN_NM": "고양시",
		"CMPNM_NM": "마임일산주엽지사",
		"INDUTYPE_NM": "회원제형태-기타1",
		"REFINE_ROADNM_ADDR": "경기도 고양시 일산서구 중앙로 1493",
		"REFINE_LOTNO_ADDR": "경기도 고양시 일산서구 주엽2동 138번지 문촌마을 제상가동 2층 2056호",
		"TELNO": "",
		"REFINE_ZIPNO": "10379",
		"REFINE_WGS84_LAT": "37.6724871385",
		"REFINE_WGS84_LOGT": "126.7547653726",
		"DATA_STD_DE": "2020-08-18"
	},
	{
		"SIGUN_NM": "고양시",
		"CMPNM_NM": "미광전기",
		"INDUTYPE_NM": "기타-기계공구",
		"REFINE_ROADNM_ADDR": "",
		"REFINE_LOTNO_ADDR": "경기도 고양시 일산서구 주엽2동 14번지 1통2반 문촌주공7단지상가 109호",
		"TELNO": "",
		"REFINE_ZIPNO": "10378",
		"REFINE_WGS84_LAT": "37.6755171788",
		"REFINE_WGS84_LOGT": "126.7564473822",
		"DATA_STD_DE": "2020-08-18"
	},
	{
		"SIGUN_NM": "고양시",
		"CMPNM_NM": "박찬훈",
		"INDUTYPE_NM": "용역 서비스-부동산 중개•임대",
		"REFINE_ROADNM_ADDR": "",
		"REFINE_LOTNO_ADDR": "경기도 고양시 일산서구 주엽2동 115 대우시티프라자229,231,232,233,234,235,260,263,265,267,268",
		"TELNO": "",
		"REFINE_ZIPNO": "",
		"REFINE_WGS84_LAT": "",
		"REFINE_WGS84_LOGT": "",
		"DATA_STD_DE": "2020-08-18"
	},
	{
		"SIGUN_NM": "고양시",
		"CMPNM_NM": "백두산목욕탕",
		"INDUTYPE_NM": "보건위생-사우나",
		"REFINE_ROADNM_ADDR": "경기도 고양시 일산서구 킨텍스로 308",
		"REFINE_LOTNO_ADDR": "경기도 고양시 일산서구 주엽2동 133번지 세경상가 지하1층",
		"TELNO": "",
		"REFINE_ZIPNO": "10384",
		"REFINE_WGS84_LAT": "37.6720825513",
		"REFINE_WGS84_LOGT": "126.7534994155",
		"DATA_STD_DE": "2020-08-18"
	},
	{
		"SIGUN_NM": "고양시",
		"CMPNM_NM": "수옵티칼시스템디자인",
		"INDUTYPE_NM": "용역 서비스-사무서비스",
		"REFINE_ROADNM_ADDR": "경기도 고양시 일산서구 중앙로 1455",
		"REFINE_LOTNO_ADDR": "경기도 고양시 일산서구 주엽2동 115번지 대우시티파라자 624",
		"TELNO": "",
		"REFINE_ZIPNO": "10387",
		"REFINE_WGS84_LAT": "37.6708974586",
		"REFINE_WGS84_LOGT": "126.7585231859",
		"DATA_STD_DE": "2020-08-18"
	},
	{
		"SIGUN_NM": "고양시",
		"CMPNM_NM": "아담치과의원",
		"INDUTYPE_NM": "의원-치과의원",
		"REFINE_ROADNM_ADDR": "경기도 고양시 일산서구 대산로 182",
		"REFINE_LOTNO_ADDR": "경기도 고양시 일산서구 주엽2동 1번지 문촌우성상가 301호",
		"TELNO": "",
		"REFINE_ZIPNO": "10371",
		"REFINE_WGS84_LAT": "37.6771866436",
		"REFINE_WGS84_LOGT": "126.7581997756",
		"DATA_STD_DE": "2020-08-18"
	},
	{
		"SIGUN_NM": "고양시",
		"CMPNM_NM": "어게인",
		"INDUTYPE_NM": "의류-정장",
		"REFINE_ROADNM_ADDR": "경기도 고양시 일산서구 킨텍스로 282",
		"REFINE_LOTNO_ADDR": "경기도 고양시 일산서구 주엽2동 126번지 신우아파트종합상가 105호",
		"TELNO": "",
		"REFINE_ZIPNO": "10384",
		"REFINE_WGS84_LAT": "37.6698571107",
		"REFINE_WGS84_LOGT": "126.7522063875",
		"DATA_STD_DE": "2020-08-18"
	},
	{
		"SIGUN_NM": "고양시",
		"CMPNM_NM": "엠비엠디자인그룹",
		"INDUTYPE_NM": "서적문구-출판 및 인쇄물",
		"REFINE_ROADNM_ADDR": "경기도 고양시 일산서구 중앙로 1493",
		"REFINE_LOTNO_ADDR": "경기도 고양시 일산서구 주엽2동 138번지 에비뉴상가 2076호",
		"TELNO": "",
		"REFINE_ZIPNO": "10379",
		"REFINE_WGS84_LAT": "37.6724871385",
		"REFINE_WGS84_LOGT": "126.7547653726",
		"DATA_STD_DE": "2020-08-18"
	},
	{
		"SIGUN_NM": "고양시",
		"CMPNM_NM": "주엽종합피아노사",
		"INDUTYPE_NM": "레져용품-악기점",
		"REFINE_ROADNM_ADDR": "",
		"REFINE_LOTNO_ADDR": "경기도 고양시 일산서구 주엽2동 136-133번지 대우레시티",
		"TELNO": "",
		"REFINE_ZIPNO": "10379",
		"REFINE_WGS84_LAT": "",
		"REFINE_WGS84_LOGT": "",
		"DATA_STD_DE": "2020-08-18"
	},
	{
		"SIGUN_NM": "고양시",
		"CMPNM_NM": "퀼트라이프",
		"INDUTYPE_NM": "문화.취미-문화취미기타",
		"REFINE_ROADNM_ADDR": "",
		"REFINE_LOTNO_ADDR": "경기도 고양시 일산서구 주엽2동 문촌4단지 삼익상가206호",
		"TELNO": "",
		"REFINE_ZIPNO": "",
		"REFINE_WGS84_LAT": "",
		"REFINE_WGS84_LOGT": "",
		"DATA_STD_DE": "2020-08-18"
	},
	{
		"SIGUN_NM": "고양시",
		"CMPNM_NM": "클라우스",
		"INDUTYPE_NM": "보건위생-안경",
		"REFINE_ROADNM_ADDR": "경기도 고양시 일산서구 중앙로 1455",
		"REFINE_LOTNO_ADDR": "경기도 고양시 일산서구 주엽2동 115번지 대우시티프라자 1층 104,105호",
		"TELNO": "",
		"REFINE_ZIPNO": "10387",
		"REFINE_WGS84_LAT": "37.6708974586",
		"REFINE_WGS84_LOGT": "126.7585231859",
		"DATA_STD_DE": "2020-08-18"
	},
	{
		"SIGUN_NM": "고양시",
		"CMPNM_NM": "하나종합공사",
		"INDUTYPE_NM": "건축자재-보일러•펌프•샷시",
		"REFINE_ROADNM_ADDR": "경기도 고양시 일산서구 주엽로 121",
		"REFINE_LOTNO_ADDR": "경기도 고양시 일산서구 주엽2동 135번지 문촌마을부영상가 101호",
		"TELNO": "",
		"REFINE_ZIPNO": "10384",
		"REFINE_WGS84_LAT": "37.6700295523",
		"REFINE_WGS84_LOGT": "126.7566722246",
		"DATA_STD_DE": "2020-08-18"
	},
	{
		"SIGUN_NM": "고양시",
		"CMPNM_NM": "하림각",
		"INDUTYPE_NM": "일반휴게음식-중국식",
		"REFINE_ROADNM_ADDR": "경기도 고양시 일산서구 주엽로 121",
		"REFINE_LOTNO_ADDR": "경기도 고양시 일산서구 주엽2동 135번지 문촌마을상가동 지하 106",
		"TELNO": "",
		"REFINE_ZIPNO": "10384",
		"REFINE_WGS84_LAT": "37.6700295523",
		"REFINE_WGS84_LOGT": "126.7566722246",
		"DATA_STD_DE": "2020-08-18"
	},
	{
		"SIGUN_NM": "고양시",
		"CMPNM_NM": "한국신용정보통신",
		"INDUTYPE_NM": "사무통신-통신기기",
		"REFINE_ROADNM_ADDR": "경기도 고양시 일산서구 대산로 165",
		"REFINE_LOTNO_ADDR": "경기도 고양시 일산서구 주엽2동 6번지 쌍용한일상가 1층 108호",
		"TELNO": "",
		"REFINE_ZIPNO": "10378",
		"REFINE_WGS84_LAT": "37.6759961572",
		"REFINE_WGS84_LOGT": "126.7595157188",
		"DATA_STD_DE": "2020-08-18"
	},
	{
		"SIGUN_NM": "고양시",
		"CMPNM_NM": "한일카센타",
		"INDUTYPE_NM": "자동차정비 유지-자동차정비",
		"REFINE_ROADNM_ADDR": "",
		"REFINE_LOTNO_ADDR": "경기도 고양시 일산서구 주엽2동 19-14번지",
		"TELNO": "",
		"REFINE_ZIPNO": "10387",
		"REFINE_WGS84_LAT": "",
		"REFINE_WGS84_LOGT": "",
		"DATA_STD_DE": "2020-08-18"
	},
	{
		"SIGUN_NM": "고양시",
		"CMPNM_NM": "헤리티지하우스",
		"INDUTYPE_NM": "신변잡화-기타잡화",
		"REFINE_ROADNM_ADDR": "",
		"REFINE_LOTNO_ADDR": "경기도 고양시 일산서구 주엽2동 606동1603호",
		"TELNO": "",
		"REFINE_ZIPNO": "",
		"REFINE_WGS84_LAT": "",
		"REFINE_WGS84_LOGT": "",
		"DATA_STD_DE": "2020-08-18"
	}
]